{"chart": {"result": [{"meta": {"currency": "USD", "symbol": "AES", "exchangeName": "NYQ", "fullExchangeName": "NYSE", "instrumentType": "EQUITY", "firstTradeDate": 677943000, "regularMarketTime": 1772727553, "hasPrePostMarketData": true, "gmtoffset": -18000, "timezone": "EST", "exchangeTimezoneName": "America/New_York", "regularMarketPrice": 14.27, "fiftyTwoWeekHigh": 17.65, "fiftyTwoWeekLow": 9.46, "regularMarketDayHigh": 14.32, "regularMarketDayLow": 14.22, "regularMarketVolume": 8916549, "longName": "The AES Corporation", "shortName": "The AES Corporation", "chartPreviousClose": 14.34, "previousClose": 14.29, "scale": 3, "priceHint": 2, "currentTradingPeriod": {"pre": {"timezone": "EST", "end": 1772721000, "start": 1772701200, "gmtoffset": -18000}, "regular": {"timezone": "EST", "end": 1772744400, "start": 1772721000, "gmtoffset": -18000}, "post": {"timezone": "EST", "end": 1772758800, "start": 1772744400, "gmtoffset": -18000}}, "tradingPeriods": {"pre": [[{"timezone": "EST", "end": 1767191400, "start": 1767171600, "gmtoffset": -18000}], [{"timezone": "EST", "end": 1767364200, "start": 1767344400, "gmtoffset": -18000}], [{"timezone": "EST", "end": 1767623400, "start": 1767603600, "gmtoffset": -18000}], [{"timezone": "EST", "end": 1767709800, "start": 1767690000, "gmtoffset": -18000}], [{"timezone": "EST", "end": 1767796200, "start": 1767776400, "gmtoffset": -18000}], [{"timezone": "EST", "end": 1767882600, "start": 1767862800, "gmtoffset": -18000}], [{"timezone": "EST", "end": 1767969000, "start": 1767949200, "gmtoffset": -18000}], [{"timezone": "EST", "end": 1768228200, "start": 1768208400, "gmtoffset": -18000}], [{"timezone": "EST", "end": 1768314600, "start": 1768294800, "gmtoffset": -18000}], [{"timezone": "EST", "end": 1768401000, "start": 1768381200, "gmtoffset": -18000}], [{"timezone": "EST", "end": 1768487400, "start": 1768467600, "gmtoffset": -18000}], [{"timezone": "EST", "end": 1768573800, "start": 1768554000, "gmtoffset": -18000}], [{"timezone": "EST", "end": 1768919400, "start": 1768899600, "gmtoffset": -18000}], [{"timezone": "EST", "end": 1769005800, "start": 1768986000, "gmtoffset": -18000}], [{"timezone": "EST", "end": 1769092200, "start": 1769072400, "gmtoffset": -18000}], [{"timezone": "EST", "end": 1769178600, "start": 1769158800, "gmtoffset": -18000}], [{"timezone": "EST", "end": 1769437800, "start": 1769418000, "gmtoffset": -18000}], [{"timezone": "EST", "end": 1769524200, "start": 1769504400, "gmtoffset": -18000}], [{"timezone": "EST", "end": 1769610600, "start": 1769590800, "gmtoffset": -18000}], [{"timezone": "EST", "end": 1769697000, "start": 1769677200, "gmtoffset": -18000}], [{"timezone": "EST", "end": 1769783400, "start": 1769763600, "gmtoffset": -18000}], [{"timezone": "EST", "end": 1770042600, "start": 1770022800, "gmtoffset": -18000}], [{"timezone": "EST", "end": 1770129000, "start": 1770109200, "gmtoffset": -18000}], [{"timezone": "EST", "end": 1770215400, "start": 1770195600, "gmtoffset": -18000}], [{"timezone": "EST", "end": 1770301800, "start": 1770282000, "gmtoffset": -18000}], [{"timezone": "EST", "end": 1770388200, "start": 1770368400, "gmtoffset": -18000}], [{"timezone": "EST", "end": 1770647400, "start": 1770627600, "gmtoffset": -18000}], [{"timezone": "EST", "end": 1770733800, "start": 1770714000, "gmtoffset": -18000}], [{"timezone": "EST", "end": 1770820200, "start": 1770800400, "gmtoffset": -18000}], [{"timezone": "EST", "end": 1770906600, "start": 1770886800, "gmtoffset": -18000}], [{"timezone": "EST", "end": 1770993000, "start": 1770973200, "gmtoffset": -18000}], [{"timezone": "EST", "end": 1771338600, "start": 1771318800, "gmtoffset": -18000}], [{"timezone": "EST", "end": 1771425000, "start": 1771405200, "gmtoffset": -18000}], [{"timezone": "EST", "end": 1771511400, "start": 1771491600, "gmtoffset": -18000}], [{"timezone": "EST", "end": 1771597800, "start": 1771578000, "gmtoffset": -18000}], [{"timezone": "EST", "end": 1771857000, "start": 1771837200, "gmtoffset": -18000}], [{"timezone": "EST", "end": 1771943400, "start": 1771923600, "gmtoffset": -18000}], [{"timezone": "EST", "end": 1772029800, "start": 1772010000, "gmtoffset": -18000}], [{"timezone": "EST", "end": 1772116200, "start": 1772096400, "gmtoffset": -18000}], [{"timezone": "EST", "end": 1772202600, "start": 1772182800, "gmtoffset": -18000}], [{"timezone": "EST", "end": 1772461800, "start": 1772442000, "gmtoffset": -18000}], [{"timezone": "EST", "end": 1772548200, "start": 1772528400, "gmtoffset": -18000}], [{"timezone": "EST", "end": 1772634600, "start": 1772614800, "gmtoffset": -18000}], [{"timezone": "EST", "end": 1772721000, "start": 1772701200, "gmtoffset": -18000}]], "post": [[{"timezone": "EST", "end": 1767229200, "start": 1767214800, "gmtoffset": -18000}], [{"timezone": "EST", "end": 1767402000, "start": 1767387600, "gmtoffset": -18000}], [{"timezone": "EST", "end": 1767661200, "start": 1767646800, "gmtoffset": -18000}], [{"timezone": "EST", "end": 1767747600, "start": 1767733200, "gmtoffset": -18000}], [{"timezone": "EST", "end": 1767834000, "start": 1767819600, "gmtoffset": -18000}], [{"timezone": "EST", "end": 1767920400, "start": 1767906000, "gmtoffset": -18000}], [{"timezone": "EST", "end": 1768006800, "start": 1767992400, "gmtoffset": -18000}], [{"timezone": "EST", "end": 1768266000, "start": 1768251600, "gmtoffset": -18000}], [{"timezone": "EST", "end": 1768352400, "start": 1768338000, "gmtoffset": -18000}], [{"timezone": "EST", "end": 1768438800, "start": 1768424400, "gmtoffset": -18000}], [{"timezone": "EST", "end": 1768525200, "start": 1768510800, "gmtoffset": -18000}], [{"timezone": "EST", "end": 1768611600, "start": 1768597200, "gmtoffset": -18000}], [{"timezone": "EST", "end": 1768957200, "start": 1768942800, "gmtoffset": -18000}], [{"timezone": "EST", "end": 1769043600, "start": 1769029200, "gmtoffset": -18000}], [{"timezone": "EST", "end": 1769130000, "start": 1769115600, "gmtoffset": -18000}], [{"timezone": "EST", "end": 1769216400, "start": 1769202000, "gmtoffset": -18000}], [{"timezone": "EST", "end": 1769475600, "start": 1769461200, "gmtoffset": -18000}], [{"timezone": "EST", "end": 1769562000, "start": 1769547600, "gmtoffset": -18000}], [{"timezone": "EST", "end": 1769648400, "start": 1769634000, "gmtoffset": -18000}], [{"timezone": "EST", "end": 1769734800, "start": 1769720400, "gmtoffset": -18000}], [{"timezone": "EST", "end": 1769821200, "start": 1769806800, "gmtoffset": -18000}], [{"timezone": "EST", "end": 1770080400, "start": 1770066000, "gmtoffset": -18000}], [{"timezone": "EST", "end": 1770166800, "start": 1770152400, "gmtoffset": -18000}], [{"timezone": "EST", "end": 1770253200, "start": 1770238800, "gmtoffset": -18000}], [{"timezone": "EST", "end": 1770339600, "start": 1770325200, "gmtoffset": -18000}], [{"timezone": "EST", "end": 1770426000, "start": 1770411600, "gmtoffset": -18000}], [{"timezone": "EST", "end": 1770685200, "start": 1770670800, "gmtoffset": -18000}], [{"timezone": "EST", "end": 1770771600, "start": 1770757200, "gmtoffset": -18000}], [{"timezone": "EST", "end": 1770858000, "start": 1770843600, "gmtoffset": -18000}], [{"timezone": "EST", "end": 1770944400, "start": 1770930000, "gmtoffset": -18000}], [{"timezone": "EST", "end": 1771030800, "start": 1771016400, "gmtoffset": -18000}], [{"timezone": "EST", "end": 1771376400, "start": 1771362000, "gmtoffset": -18000}], [{"timezone": "EST", "end": 1771462800, "start": 1771448400, "gmtoffset": -18000}], [{"timezone": "EST", "end": 1771549200, "start": 1771534800, "gmtoffset": -18000}], [{"timezone": "EST", "end": 1771635600, "start": 1771621200, "gmtoffset": -18000}], [{"timezone": "EST", "end": 1771894800, "start": 1771880400, "gmtoffset": -18000}], [{"timezone": "EST", "end": 1771981200, "start": 1771966800, "gmtoffset": -18000}], [{"timezone": "EST", "end": 1772067600, "start": 1772053200, "gmtoffset": -18000}], [{"timezone": "EST", "end": 1772154000, "start": 1772139600, "gmtoffset": -18000}], [{"timezone": "EST", "end": 1772240400, "start": 1772226000, "gmtoffset": -18000}], [{"timezone": "EST", "end": 1772499600, "start": 1772485200, "gmtoffset": -18000}], [{"timezone": "EST", "end": 1772586000, "start": 1772571600, "gmtoffset": -18000}], [{"timezone": "EST", "end": 1772672400, "start": 1772658000, "gmtoffset": -18000}], [{"timezone": "EST", "end": 1772758800, "start": 1772744400, "gmtoffset": -18000}]], "regular": [[{"timezone": "EST", "end": 1767214800, "start": 1767191400, "gmtoffset": -18000}], [{"timezone": "EST", "end": 1767387600, "start": 1767364200, "gmtoffset": -18000}], [{"timezone": "EST", "end": 1767646800, "start": 1767623400, "gmtoffset": -18000}], [{"timezone": "EST", "end": 1767733200, "start": 1767709800, "gmtoffset": -18000}], [{"timezone": "EST", "end": 1767819600, "start": 1767796200, "gmtoffset": -18000}], [{"timezone": "EST", "end": 1767906000, "start": 1767882600, "gmtoffset": -18000}], [{"timezone": "EST", "end": 1767992400, "start": 1767969000, "gmtoffset": -18000}], [{"timezone": "EST", "end": 1768251600, "start": 1768228200, "gmtoffset": -18000}], [{"timezone": "EST", "end": 1768338000, "start": 1768314600, "gmtoffset": -18000}], [{"timezone": "EST", "end": 1768424400, "start": 1768401000, "gmtoffset": -18000}], [{"timezone": "EST", "end": 1768510800, "start": 1768487400, "gmtoffset": -18000}], [{"timezone": "EST", "end": 1768597200, "start": 1768573800, "gmtoffset": -18000}], [{"timezone": "EST", "end": 1768942800, "start": 1768919400, "gmtoffset": -18000}], [{"timezone": "EST", "end": 1769029200, "start": 1769005800, "gmtoffset": -18000}], [{"timezone": "EST", "end": 1769115600, "start": 1769092200, "gmtoffset": -18000}], [{"timezone": "EST", "end": 1769202000, "start": 1769178600, "gmtoffset": -18000}], [{"timezone": "EST", "end": 1769461200, "start": 1769437800, "gmtoffset": -18000}], [{"timezone": "EST", "end": 1769547600, "start": 1769524200, "gmtoffset": -18000}], [{"timezone": "EST", "end": 1769634000, "start": 1769610600, "gmtoffset": -18000}], [{"timezone": "EST", "end": 1769720400, "start": 1769697000, "gmtoffset": -18000}], [{"timezone": "EST", "end": 1769806800, "start": 1769783400, "gmtoffset": -18000}], [{"timezone": "EST", "end": 1770066000, "start": 1770042600, "gmtoffset": -18000}], [{"timezone": "EST", "end": 1770152400, "start": 1770129000, "gmtoffset": -18000}], [{"timezone": "EST", "end": 1770238800, "start": 1770215400, "gmtoffset": -18000}], [{"timezone": "EST", "end": 1770325200, "start": 1770301800, "gmtoffset": -18000}], [{"timezone": "EST", "end": 1770411600, "start": 1770388200, "gmtoffset": -18000}], [{"timezone": "EST", "end": 1770670800, "start": 1770647400, "gmtoffset": -18000}], [{"timezone": "EST", "end": 1770757200, "start": 1770733800, "gmtoffset": -18000}], [{"timezone": "EST", "end": 1770843600, "start": 1770820200, "gmtoffset": -18000}], [{"timezone": "EST", "end": 1770930000, "start": 1770906600, "gmtoffset": -18000}], [{"timezone": "EST", "end": 1771016400, "start": 1770993000, "gmtoffset": -18000}], [{"timezone": "EST", "end": 1771362000, "start": 1771338600, "gmtoffset": -18000}], [{"timezone": "EST", "end": 1771448400, "start": 1771425000, "gmtoffset": -18000}], [{"timezone": "EST", "end": 1771534800, "start": 1771511400, "gmtoffset": -18000}], [{"timezone": "EST", "end": 1771621200, "start": 1771597800, "gmtoffset": -18000}], [{"timezone": "EST", "end": 1771880400, "start": 1771857000, "gmtoffset": -18000}], [{"timezone": "EST", "end": 1771966800, "start": 1771943400, "gmtoffset": -18000}], [{"timezone": "EST", "end": 1772053200, "start": 1772029800, "gmtoffset": -18000}], [{"timezone": "EST", "end": 1772139600, "start": 1772116200, "gmtoffset": -18000}], [{"timezone": "EST", "end": 1772226000, "start": 1772202600, "gmtoffset": -18000}], [{"timezone": "EST", "end": 1772485200, "start": 1772461800, "gmtoffset": -18000}], [{"timezone": "EST", "end": 1772571600, "start": 1772548200, "gmtoffset": -18000}], [{"timezone": "EST", "end": 1772658000, "start": 1772634600, "gmtoffset": -18000}], [{"timezone": "EST", "end": 1772744400, "start": 1772721000, "gmtoffset": -18000}]]}, "dataGranularity": "1h", "range": "", "validRanges": ["1d", "5d", "1mo", "3mo", "6mo", "1y", "2y", "5y", "10y", "ytd", "max"]}, "timestamp": [1767344400, 1767348000, 1767351600, 1767355200, 1767358800, 1767362400, 1767364200, 1767367800, 1767371400, 1767375000, 1767378600, 1767382200, 1767385800, 1767387600, 1767391200, 1767394800, 1767603600, 1767607200, 1767610800, 1767614400, 1767618000, 1767621600, 1767623400, 1767627000, 1767630600, 1767634200, 1767637800, 1767641400, 1767645000, 1767646800, 1767650400, 1767654000, 1767690000, 1767693600, 1767697200, 1767700800, 1767704400, 1767708000, 1767709800, 1767713400, 1767717000, 1767720600, 1767724200, 1767727800, 1767731400, 1767733200, 1767736800, 1767740400, 1767776400, 1767780000, 1767783600, 1767787200, 1767790800, 1767794400, 1767796200, 1767799800, 1767803400, 1767807000, 1767810600, 1767814200, 1767817800, 1767819600, 1767823200, 1767826800, 1767862800, 1767866400, 1767870000, 1767873600, 1767877200, 1767880800, 1767882600, 1767886200, 1767889800, 1767893400, 1767897000, 1767900600, 1767904200, 1767906000, 1767909600, 1767913200, 1767949200, 1767952800, 1767956400, 1767960000, 1767963600, 1767967200, 1767969000, 1767972600, 1767976200, 1767979800, 1767983400, 1767987000, 1767990600, 1767992400, 1767996000, 1767999600, 1768208400, 1768212000, 1768215600, 1768219200, 1768222800, 1768226400, 1768228200, 1768231800, 1768235400, 1768239000, 1768242600, 1768246200, 1768249800, 1768251600, 1768255200, 1768258800, 1768294800, 1768298400, 1768302000, 1768305600, 1768309200, 1768312800, 1768314600, 1768318200, 1768321800, 1768325400, 1768329000, 1768332600, 1768336200, 1768338000, 1768341600, 1768345200, 1768381200, 1768384800, 1768388400, 1768392000, 1768395600, 1768399200, 1768401000, 1768404600, 1768408200, 1768411800, 1768415400, 1768419000, 1768422600, 1768424400, 1768428000, 1768431600, 1768467600, 1768471200, 1768474800, 1768478400, 1768482000, 1768485600, 1768487400, 1768491000, 1768494600, 1768498200, 1768501800, 1768505400, 1768509000, 1768510800, 1768514400, 1768518000, 1768554000, 1768557600, 1768561200, 1768564800, 1768568400, 1768572000, 1768573800, 1768577400, 1768581000, 1768584600, 1768588200, 1768591800, 1768595400, 1768597200, 1768600800, 1768604400, 1768899600, 1768903200, 1768906800, 1768910400, 1768914000, 1768917600, 1768919400, 1768923000, 1768926600, 1768930200, 1768933800, 1768937400, 1768941000, 1768942800, 1768946400, 1768950000, 1768986000, 1768989600, 1768993200, 1768996800, 1769000400, 1769004000, 1769005800, 1769009400, 1769013000, 1769016600, 1769020200, 1769023800, 1769027400, 1769029200, 1769032800, 1769036400, 1769072400, 1769079600, 1769083200, 1769086800, 1769090400, 1769092200, 1769095800, 1769099400, 1769103000, 1769106600, 1769110200, 1769113800, 1769115600, 1769119200, 1769122800, 1769158800, 1769162400, 1769166000, 1769169600, 1769173200, 1769176800, 1769178600, 1769182200, 1769185800, 1769189400, 1769193000, 1769196600, 1769200200, 1769202000, 1769205600, 1769209200, 1769418000, 1769421600, 1769425200, 1769428800, 1769432400, 1769436000, 1769437800, 1769441400, 1769445000, 1769448600, 1769452200, 1769455800, 1769459400, 1769461200, 1769464800, 1769468400, 1769504400, 1769508000, 1769511600, 1769515200, 1769518800, 1769522400, 1769524200, 1769527800, 1769531400, 1769535000, 1769538600, 1769542200, 1769545800, 1769547600, 1769551200, 1769554800, 1769590800, 1769594400, 1769598000, 1769601600, 1769605200, 1769608800, 1769610600, 1769614200, 1769617800, 1769621400, 1769625000, 1769628600, 1769632200, 1769634000, 1769637600, 1769641200, 1769677200, 1769680800, 1769684400, 1769688000, 1769691600, 1769695200, 1769697000, 1769700600, 1769704200, 1769707800, 1769711400, 1769715000, 1769718600, 1769720400, 1769724000, 1769727600, 1769763600, 1769767200, 1769770800, 1769774400, 1769778000, 1769781600, 1769783400, 1769787000, 1769790600, 1769794200, 1769797800, 1769801400, 1769805000, 1770042600, 1770046200, 1770049800, 1770053400, 1770057000, 1770060600, 1770064200, 1770066000, 1770069600, 1770073200, 1770109200, 1770112800, 1770116400, 1770120000, 1770123600, 1770127200, 1770129000, 1770132600, 1770136200, 1770139800, 1770143400, 1770147000, 1770150600, 1770152400, 1770156000, 1770159600, 1770195600, 1770199200, 1770202800, 1770206400, 1770210000, 1770213600, 1770215400, 1770219000, 1770222600, 1770226200, 1770229800, 1770233400, 1770237000, 1770238800, 1770242400, 1770246000, 1770282000, 1770285600, 1770289200, 1770292800, 1770296400, 1770300000, 1770301800, 1770305400, 1770309000, 1770312600, 1770316200, 1770319800, 1770323400, 1770325200, 1770328800, 1770332400, 1770368400, 1770372000, 1770375600, 1770379200, 1770382800, 1770386400, 1770388200, 1770391800, 1770395400, 1770399000, 1770402600, 1770406200, 1770409800, 1770411600, 1770415200, 1770418800, 1770627600, 1770631200, 1770634800, 1770638400, 1770642000, 1770645600, 1770647400, 1770651000, 1770654600, 1770658200, 1770661800, 1770665400, 1770669000, 1770670800, 1770674400, 1770678000, 1770714000, 1770717600, 1770721200, 1770724800, 1770728400, 1770732000, 1770733800, 1770737400, 1770741000, 1770744600, 1770748200, 1770751800, 1770755400, 1770757200, 1770760800, 1770764400, 1770800400, 1770804000, 1770807600, 1770811200, 1770814800, 1770818400, 1770820200, 1770823800, 1770827400, 1770831000, 1770834600, 1770838200, 1770841800, 1770843600, 1770847200, 1770850800, 1770886800, 1770890400, 1770894000, 1770897600, 1770901200, 1770904800, 1770906600, 1770910200, 1770913800, 1770917400, 1770921000, 1770924600, 1770928200, 1770930000, 1770933600, 1770937200, 1770973200, 1770976800, 1770980400, 1770984000, 1770987600, 1770991200, 1770993000, 1770996600, 1771000200, 1771003800, 1771007400, 1771011000, 1771014600, 1771016400, 1771020000, 1771023600, 1771318800, 1771322400, 1771326000, 1771329600, 1771333200, 1771336800, 1771338600, 1771342200, 1771345800, 1771349400, 1771353000, 1771356600, 1771360200, 1771362000, 1771365600, 1771369200, 1771405200, 1771408800, 1771412400, 1771416000, 1771419600, 1771423200, 1771425000, 1771428600, 1771432200, 1771435800, 1771439400, 1771443000, 1771446600, 1771448400, 1771452000, 1771455600, 1771491600, 1771495200, 1771502400, 1771506000, 1771509600, 1771511400, 1771515000, 1771518600, 1771522200, 1771525800, 1771529400, 1771533000, 1771534800, 1771538400, 1771542000, 1771578000, 1771581600, 1771585200, 1771588800, 1771592400, 1771596000, 1771597800, 1771601400, 1771605000, 1771608600, 1771612200, 1771615800, 1771619400, 1771621200, 1771624800, 1771628400, 1771837200, 1771840800, 1771844400, 1771848000, 1771851600, 1771855200, 1771857000, 1771860600, 1771864200, 1771867800, 1771871400, 1771875000, 1771878600, 1771880400, 1771884000, 1771887600, 1771923600, 1771927200, 1771930800, 1771934400, 1771938000, 1771941600, 1771943400, 1771947000, 1771950600, 1771954200, 1771957800, 1771961400, 1771965000, 1771966800, 1771970400, 1771974000, 1772010000, 1772013600, 1772017200, 1772020800, 1772024400, 1772028000, 1772029800, 1772033400, 1772037000, 1772040600, 1772044200, 1772047800, 1772051400, 1772053200, 1772056800, 1772060400, 1772096400, 1772100000, 1772103600, 1772107200, 1772110800, 1772114400, 1772116200, 1772119800, 1772123400, 1772127000, 1772130600, 1772134200, 1772137800, 1772139600, 1772143200, 1772146800, 1772182800, 1772186400, 1772190000, 1772193600, 1772197200, 1772200800, 1772202600, 1772206200, 1772209800, 1772213400, 1772217000, 1772220600, 1772224200, 1772226000, 1772229600, 1772233200, 1772442000, 1772445600, 1772449200, 1772452800, 1772456400, 1772460000, 1772461800, 1772465400, 1772469000, 1772472600, 1772476200, 1772479800, 1772483400, 1772485200, 1772488800, 1772492400, 1772528400, 1772532000, 1772535600, 1772539200, 1772542800, 1772546400, 1772548200, 1772551800, 1772555400, 1772559000, 1772562600, 1772566200, 1772569800, 1772571600, 1772575200, 1772578800, 1772614800, 1772618400, 1772622000, 1772625600, 1772629200, 1772632800, 1772634600, 1772638200, 1772641800, 1772645400, 1772649000, 1772652600, 1772656200, 1772658000, 1772661600, 1772665200, 1772701200, 1772704800, 1772708400, 1772712000, 1772715600, 1772719200, 1772721000, 1772724600, 1772727553], "indicators": {"quote": [{"open": [14.4, 14.48, 14.46, 14.42, 14.41, 14.4, 14.510000228881836, 14.539999961853027, 14.619999885559082, 14.694999694824219, 14.635000228881836, 14.739999771118164, 14.824999809265137, 14.82, 14.84, 14.86, 14.85, 14.87, 14.86, 14.85, 14.87, 14.87, 14.970000267028809, 14.6899995803833, 14.520000457763672, 14.579999923706055, 14.594499588012695, 14.6850004196167, 14.720000267028809, 14.73, 14.7, 14.74, 14.75, 14.68, 14.73, 14.74, 14.77, 14.78, 14.829899787902832, 14.839799880981445, 14.854999542236328, 14.885000228881836, 14.875, 14.864999771118164, 14.874500274658203, 14.9, 14.96, 14.85, 14.88, 14.89, 14.91, 14.89, 14.91, 14.92, 14.850000381469727, 14.654999732971191, 14.585000038146973, 14.569999694824219, 14.536700248718262, 14.569999694824219, 14.475000381469727, 14.45, 14.6471, 14.5, 14.47, 14.43, 14.4, 14.41, 14.41, 14.41, 14.4399995803833, 14.329700469970703, 14.384400367736816, 14.319999694824219, 14.329999923706055, 14.385000228881836, 14.25, 14.2099, 14.23, 14.25, 14.27, 14.24, 14.23, 14.27, 14.275, 14.3, 14.329999923706055, 14.579999923706055, 14.600000381469727, 14.520000457763672, 14.444600105285645, 14.4350004196167, 14.380000114440918, 14.32, 14.36, 14.4171, 14.4, 14.37, 14.36, 14.33, 14.34, 14.33, 14.25, 14.125699996948242, 14.140000343322754, 14.204999923706055, 14.215900421142578, 14.104999542236328, 14.050100326538086, 14.04, 14.0705, 14.06, 14.11, 14.08, 14.06, 14.07, 14.08, 14.04, 14.050000190734863, 14.03499984741211, 14.045000076293945, 14.074999809265137, 14.050000190734863, 14.029999732971191, 13.984999656677246, 13.97, 13.98, 14.01, 14.01, 14.01, 13.97, 13.98, 13.97, 13.97, 13.899999618530273, 13.9350004196167, 14.050000190734863, 14.185500144958496, 14.125, 14.140000343322754, 14.0649995803833, 14.0, 14.04, 14.01, 14.05, 14.18, 14.18, 14.05, 14.03, 14.04, 14.079999923706055, 14.199999809265137, 14.270000457763672, 14.315999984741211, 14.484999656677246, 14.550000190734863, 14.454999923706055, 14.44, 14.4899, 14.48, 14.52, 14.55, 14.53, 14.53, 14.47, 14.43, 14.319999694824219, 14.579999923706055, 14.4350004196167, 14.329999923706055, 14.300000190734863, 14.1850004196167, 14.175000190734863, 14.19, 14.26, 14.2, 14.2, 14.08, 14.0, 13.98, 14.08, 14.05, 13.949999809265137, 13.890000343322754, 13.765000343322754, 13.800000190734863, 13.819999694824219, 13.71500015258789, 13.75, 13.77, 13.79, 13.7998, 13.81, 13.81, 13.87, 13.87, 13.85, 13.82, 14.039999961853027, 14.164999961853027, 14.175000190734863, 14.069999694824219, 14.03499984741211, 14.119999885559082, 14.164999961853027, 14.24, 14.26, 14.28, 14.26, 14.34, 14.33, 14.32, 14.33, 14.420000076293945, 14.3100004196167, 14.5600004196167, 14.520000457763672, 14.625, 14.59529972076416, 14.614999771118164, 14.61, 14.65, 14.6599, 14.65, 14.61, 14.61, 14.65, 14.64, 14.59, 14.569999694824219, 14.3100004196167, 14.300000190734863, 14.189900398254395, 14.234999656677246, 14.265000343322754, 14.225000381469727, 14.22, 14.25, 14.2423, 14.29, 14.3, 14.23, 14.22, 14.26, 14.31, 14.300000190734863, 14.479900360107422, 14.654999732971191, 14.824999809265137, 14.670000076293945, 14.71500015258789, 14.628700256347656, 14.62, 14.85, 14.68, 14.75, 14.7, 14.7, 14.685, 14.69, 14.71, 14.739999771118164, 14.854499816894531, 14.944999694824219, 14.865799903869629, 14.864999771118164, 14.869999885559082, 14.875, 14.92, 14.92, 14.92, 14.88, 14.95, 14.95, 14.96, 14.93, 14.94, 14.989999771118164, 14.885000228881836, 14.944999694824219, 14.904999732971191, 14.979999542236328, 15.0, 15.194999694824219, 15.19, 15.27, 15.26, 15.17, 15.19, 15.2, 15.22, 15.255, 15.25, 15.199999809265137, 14.920000076293945, 14.824999809265137, 14.939900398254395, 14.994999885559082, 15.085000038146973, 15.005000114440918, 15.04, 15.14, 15.1, 14.82, 14.72, 14.72, 14.78, 14.84, 14.818, 14.829999923706055, null, null, null, null, null, null, null, null, null, null, 14.760000228881836, 14.854999542236328, 14.760000228881836, 14.74, 14.79, 16.27, 15.75, 15.54, 15.63, 15.64, 15.9, 15.92, 15.729999542236328, 16.024999618530273, 16.0049991607666, 15.920000076293945, 15.654999732971191, 15.729999542236328, 15.9350004196167, 16.09, 16.08, 16.08, 16.02, 16.11, 16.12, 16.09, 16.09, 16.05, 15.880000114440918, 15.6850004196167, 15.880000114440918, 15.774999618530273, 15.734999656677246, 15.78499984741211, 15.8149995803833, 15.75, 15.725, 15.78, 15.73, 15.56, 15.65, 15.7, 15.74, 15.6131, 15.510000228881836, 15.5649995803833, 15.569999694824219, 15.524999618530273, 15.555000305175781, 15.645000457763672, 15.628199577331543, 15.59, 15.56, 15.59, 15.59, 15.71, 15.74, 15.77, 15.79, 15.83, 15.885000228881836, 15.774999618530273, 15.800000190734863, 15.984999656677246, 16.0049991607666, 16.09000015258789, 15.994999885559082, 16.05, 16.0754, 16.0899, 16.2, 16.1, 16.06, 16.07, 16.06, 16.06, 15.979999542236328, 15.864999771118164, 15.994999885559082, 16.05500030517578, 16.110000610351562, 16.225000381469727, 16.165000915527344, 16.06, 16.02, 16.02, 16.2, 16.11, 16.09, 16.09, 16.1, 16.07, 16.09000015258789, 15.9350004196167, 15.975000381469727, 16.1299991607666, 16.174999237060547, 16.218000411987305, 16.219999313354492, 16.25, 16.3, 16.25, 16.37, 16.36, 16.27, 16.28, 16.29, 16.3, 16.420000076293945, 16.329999923706055, 16.420000076293945, 16.540000915527344, 16.459999084472656, 16.40999984741211, 16.424999237060547, 16.44, 16.48, 16.45, 16.5, 16.55, 16.47, 16.54, 16.52, 16.5001, 16.420000076293945, 16.635000228881836, 16.389999389648438, 16.2450008392334, 16.190000534057617, 16.350000381469727, 16.309999465942383, 16.2, 16.24, 16.18, 16.3, 16.26, 16.21, 16.25, 16.19, 16.19, 16.040000915527344, 16.489999771118164, 16.540000915527344, 16.405000686645508, 16.389999389648438, 16.360000610351562, 16.30500030517578, 16.28, 16.26, 16.23, 16.37, 16.29, 16.29, 16.27, 16.3, 16.27, 16.290000915527344, 16.325000762939453, 16.375, 16.354999542236328, 16.315000534057617, 16.344999313354492, 16.375, 16.39, 16.44, 16.42, 16.36, 16.36, 16.36, 16.44, 16.41, 16.42, 16.420000076293945, 16.364999771118164, 16.354999542236328, 16.290000915527344, 16.350000381469727, 16.31999969482422, 16.229999542236328, 16.29, 16.25, 16.36, 16.32, 16.35, 16.28, 16.28, 16.29, 16.239999771118164, 16.239999771118164, 16.299999237060547, 16.31999969482422, 16.344999313354492, 16.299999237060547, 16.334999084472656, 16.36, 16.2812, 16.3302, 16.4, 16.48, 16.43, 16.38, 16.36, 16.36, 16.25, 16.295000076293945, 16.334999084472656, 16.40999984741211, 16.420000076293945, 16.420000076293945, 16.469999313354492, 16.51, 16.4, 16.45, 16.46, 16.4, 16.42, 16.4, 16.32, 16.36, 16.360000610351562, 16.19499969482422, 16.135000228881836, 16.229999542236328, 16.31999969482422, 16.375, 16.389999389648438, 16.26, 16.27, 16.27, 16.2886, 16.2886, 16.3, 16.3, 16.46, 16.48, 16.329999923706055, 16.295000076293945, 16.395000457763672, 16.315000534057617, 16.325000762939453, 16.41990089416504, 16.354999542236328, 16.27, 16.3448, 16.347, 16.4, 16.41, 16.45, 16.43, 16.4, 16.35, 16.420000076293945, 16.309999465942383, 16.44499969482422, 16.34000015258789, 16.354999542236328, 16.334999084472656, 16.334999084472656, 16.37, 16.4459, 16.42, 16.43, 16.45, 16.45, 16.44, 16.42, 16.4338, 16.3700008392334, 16.020000457763672, 16.204999923706055, 15.975000381469727, 16.049999237060547, 16.06999969482422, 16.155000686645508, 16.25, 16.16, 16.17, 16.16, 16.21, 16.0, 16.14, 16.44, 16.65, 17.059999465942383, 17.270000457763672, 17.399999618530273, 17.227699279785156, 17.149999618530273, 17.209999084472656, 17.209999084472656, 17.28, 17.205, 17.22, 16.9, 16.81, 16.99, 17.09, 14.41, 14.44, 14.345000267028809, 14.295000076293945, 14.273799896240234, 14.265000343322754, 14.300000190734863, 14.3149995803833, 14.295000076293945, 14.2, 14.2302, 14.24, 14.22, 14.22, 14.21, 14.22, 14.22, 14.22, 14.1899995803833, 14.16100025177002, 14.15999984741211, 14.229999542236328, 14.229999542236328, 14.225000381469727, 14.234999656677246, 14.18, 14.18, 14.1602, 14.11, 14.25, 14.2, 14.31, 14.27, 14.26, 14.180000305175781, 14.225000381469727, 14.255000114440918, 14.260000228881836, 14.274999618530273, 14.265000343322754, 14.260000228881836, 14.29, 14.27, 14.26, 14.26, 14.25, 14.25, 14.23, 14.25, 14.22, 14.229999542236328, 14.274999618530273, 14.270000457763672], "low": [14.4, 14.46, 14.45, 14.4, 14.38, 14.38, 14.381400108337402, 14.53499984741211, 14.59000015258789, 14.619999885559082, 14.630000114440918, 14.734000205993652, 14.739999771118164, 14.8, 14.82, 14.8, 14.85, 14.86, 14.85, 14.84, 14.8, 14.84, 14.680000305175781, 14.460000038146973, 14.5, 14.569999694824219, 14.594499588012695, 14.680000305175781, 14.694999694824219, 14.6, 14.7, 14.71, 14.72, 14.68, 14.73, 14.74, 14.68, 14.74, 14.6850004196167, 14.739999771118164, 14.850000381469727, 14.805000305175781, 14.824999809265137, 14.850000381469727, 14.84000015258789, 14.89, 14.85, 14.8, 14.88, 14.89, 14.89, 14.89, 14.84, 14.92, 14.579999923706055, 14.529999732971191, 14.550100326538086, 14.529999732971191, 14.510000228881836, 14.460000038146973, 14.430000305175781, 14.42, 14.45, 14.41, 14.4, 14.39, 14.4, 14.41, 14.38, 14.4048, 14.295000076293945, 14.244999885559082, 14.295000076293945, 14.289999961853027, 14.3100004196167, 14.239999771118164, 14.204999923706055, 14.2011, 14.22, 14.22, 14.23, 14.23, 14.23, 14.25, 14.14, 14.2, 14.289999961853027, 14.521599769592285, 14.489999771118164, 14.4399995803833, 14.399999618530273, 14.369999885559082, 14.3149995803833, 14.3, 14.36, 14.35, 14.28, 14.34, 14.34, 14.32, 14.3, 14.31, 13.899999618530273, 14.104999542236328, 14.119999885559082, 14.180000305175781, 14.100000381469727, 14.045000076293945, 14.020000457763672, 14.04, 14.04, 14.04, 14.08, 14.05, 14.04, 14.06, 14.02, 14.0, 13.989999771118164, 14.005000114440918, 13.904999732971191, 14.024999618530273, 14.0, 13.970000267028809, 13.9350004196167, 13.95, 13.97, 13.98, 13.97, 13.97, 13.95, 13.95, 13.95, 13.9542, 13.890000343322754, 13.91450023651123, 14.050000190734863, 14.109999656677246, 14.100000381469727, 14.0600004196167, 13.979999542236328, 13.99, 14.0, 14.0, 14.05, 14.18, 14.05, 14.02, 13.93, 14.01, 14.029999732971191, 14.1899995803833, 14.199999809265137, 14.25, 14.479999542236328, 14.350000381469727, 14.399999618530273, 14.08, 14.44, 14.44, 14.52, 14.52, 14.53, 14.45, 14.4, 14.35, 14.319999694824219, 14.359999656677246, 14.289999961853027, 14.239999771118164, 14.175000190734863, 14.140000343322754, 14.164999961853027, 14.15, 14.17, 14.17, 14.01, 13.93, 13.97, 13.98, 13.8728, 14.001, 13.649999618530273, 13.725000381469727, 13.744999885559082, 13.720000267028809, 13.710000038146973, 13.630000114440918, 13.6899995803833, 13.72, 13.77, 13.77, 13.81, 13.78, 13.87, 13.79, 13.77, 13.81, 14.010000228881836, 14.085000038146973, 14.029999732971191, 14.010000228881836, 13.984999656677246, 14.100000381469727, 14.15999984741211, 14.1819, 14.24, 14.25, 14.26, 14.32, 14.3, 14.29, 14.32, 14.130000114440918, 14.300000190734863, 14.475000381469727, 14.510000228881836, 14.579999923706055, 14.5649995803833, 14.529999732971191, 14.6, 14.61, 14.65, 14.59, 14.6, 14.56, 14.59, 14.55, 14.58, 14.28499984741211, 14.229999542236328, 14.175000190734863, 14.149999618530273, 14.1850004196167, 14.204999923706055, 14.1899995803833, 14.2, 14.2, 14.2038, 14.29, 14.24, 14.21, 14.22, 14.18, 14.24, 14.270000457763672, 14.444999694824219, 14.630000114440918, 14.65999984741211, 14.654999732971191, 14.609999656677246, 14.600000381469727, 14.62, 14.63, 14.63, 14.67, 14.7, 14.7, 14.64, 14.64, 14.71, 14.520000457763672, 14.835000038146973, 14.845000267028809, 14.819999694824219, 14.850000381469727, 14.800000190734863, 14.850000381469727, 14.82, 14.9, 14.9051, 14.88, 14.95, 14.95, 14.91, 14.88, 14.93, 14.859999656677246, 14.845000267028809, 14.880000114440918, 14.859999656677246, 14.975000381469727, 14.954999923706055, 15.113900184631348, 14.934179, 15.23, 15.19, 15.17, 15.18, 15.2, 15.22, 15.08, 15.25, 14.925000190734863, 14.604999542236328, 14.8100004196167, 14.899999618530273, 14.894599914550781, 14.979999542236328, 14.979999542236328, 15.0304, 15.08, 15.08, 14.71, 14.64, 14.72, 14.78, 14.6129, 14.8, 14.739999771118164, null, null, null, null, null, null, null, null, null, null, 14.744999885559082, 14.6899995803833, 14.6899995803833, 14.73, 14.73, 15.55, 15.6, 15.52, 15.55, 15.56, 15.22, 15.7, 15.449999809265137, 15.970000267028809, 15.829999923706055, 15.649999618530273, 15.619999885559082, 15.680000305175781, 15.904999732971191, 15.93, 16.05, 16.08, 16.02, 16.02, 16.09, 16.05, 15.9, 16.0, 15.539999961853027, 15.569999694824219, 15.729999542236328, 15.710000038146973, 15.630000114440918, 15.78499984741211, 15.6899995803833, 15.61, 15.65, 15.65, 15.5, 15.55, 15.56, 15.68, 15.53, 15.61, 15.350000381469727, 15.510000228881836, 15.4350004196167, 15.484999656677246, 15.454999923706055, 15.585000038146973, 15.550000190734863, 15.5, 15.5, 15.5, 15.59, 15.71, 15.71, 15.73, 15.42, 15.76, 15.770000457763672, 15.71500015258789, 15.789999961853027, 15.920000076293945, 16.0049991607666, 15.960000038146973, 15.984999656677246, 16.01, 16.05, 16.06, 16.1, 16.06, 16.05, 16.055, 16.0032, 16.0, 15.850000381469727, 15.864999771118164, 15.920000076293945, 16.045000076293945, 16.079999923706055, 16.15999984741211, 16.049999237060547, 16.01, 16.01, 16.01, 16.08, 16.09, 16.09, 16.09, 16.06, 16.07, 15.8100004196167, 15.84000015258789, 15.96500015258789, 16.1299991607666, 16.145000457763672, 16.204999923706055, 16.190000534057617, 16.19, 16.25, 16.25, 16.36, 16.27, 16.2, 16.27, 16.17, 16.3, 16.290000915527344, 16.270000457763672, 16.415000915527344, 16.405000686645508, 16.3700008392334, 16.395000457763672, 16.399999618530273, 16.35, 16.41, 16.45, 16.48, 16.47, 16.47, 16.51, 16.46, 16.5, 16.329999923706055, 16.389999389648438, 16.18000030517578, 16.125, 16.170000076293945, 16.309999465942383, 16.174999237060547, 16.1, 16.18, 16.15, 16.26, 16.21, 16.19, 16.16, 16.15, 16.17, 15.979999542236328, 16.34000015258789, 16.399999618530273, 16.354999542236328, 16.329999923706055, 16.274999618530273, 16.2450008392334, 16.2, 16.2, 16.2139, 16.28, 16.27, 16.27, 16.24, 16.21, 16.2397, 16.15999984741211, 16.21500015258789, 16.290000915527344, 16.290000915527344, 16.295000076293945, 16.299999237060547, 16.354999542236328, 16.32, 16.39, 16.35, 16.36, 16.36, 16.36, 16.42, 16.32, 16.39, 16.2549991607666, 16.31999969482422, 16.264999389648438, 16.28499984741211, 16.295000076293945, 16.219999313354492, 16.229999542236328, 16.22, 16.24, 16.24, 16.32, 16.25, 16.25, 16.25, 16.25, 16.165000915527344, 16.239999771118164, 16.260000228881836, 16.299999237060547, 16.280000686645508, 16.270000457763672, 16.315000534057617, 16.27, 16.2812, 16.3302, 16.4, 16.43, 16.38, 16.36, 16.33, 16.31, 16.059999465942383, 16.280000686645508, 16.315000534057617, 16.389999389648438, 16.399999618530273, 16.34000015258789, 16.434999465942383, 16.35, 16.4, 16.426, 16.35, 16.4, 16.38, 16.31, 16.27, 16.3, 16.15999984741211, 16.040000915527344, 16.03499984741211, 16.184999465942383, 16.295000076293945, 16.280000686645508, 16.209999084472656, 16.245, 16.27, 16.27, 16.2886, 16.2886, 16.3, 16.3, 16.2224, 16.335, 16.125, 16.2549991607666, 16.290000915527344, 16.299999237060547, 16.309999465942383, 16.350000381469727, 16.25, 16.27, 16.3, 16.3, 16.39, 16.4, 16.43, 16.36, 16.27, 16.3, 16.260000228881836, 16.270000457763672, 16.309999465942383, 16.329999923706055, 16.329999923706055, 16.31450080871582, 16.334999084472656, 16.31, 16.39, 16.41, 16.43, 16.45, 16.4, 16.4, 16.37, 16.35, 16.014999389648438, 16.010000228881836, 15.970000267028809, 15.920000076293945, 16.040000915527344, 16.06999969482422, 16.149999618530273, 16.1264, 16.14, 16.16, 16.16, 16.0, 16.0, 16.14, 16.0, 16.6, 16.897199630737305, 17.219999313354492, 17.170000076293945, 17.094999313354492, 17.1200008392334, 17.0, 17.145000457763672, 17.05, 17.05, 17.19, 16.67, 16.81, 16.99, 14.03, 14.12, 14.32, 14.244999885559082, 14.25, 14.239999771118164, 14.260000228881836, 14.260000228881836, 14.289999961853027, 14.199999809265137, 14.19, 14.21, 14.22, 14.18, 14.21, 14.2, 14.2, 14.15, 14.18, 14.109999656677246, 14.140000343322754, 14.149999618530273, 14.194999694824219, 14.210000038146973, 14.220000267028809, 14.170000076293945, 14.15, 14.15, 14.14, 14.11, 14.17, 14.2, 14.25, 14.11, 14.24, 14.15999984741211, 14.220000267028809, 14.229999542236328, 14.260000228881836, 14.260000228881836, 14.25, 14.255000114440918, 14.25, 14.25, 14.26, 14.24, 14.24, 14.24, 14.23, 14.2, 14.22, 14.220000267028809, 14.25, 14.270000457763672], "high": [14.48, 14.48, 14.48, 14.44, 14.5467, 14.4, 14.5600004196167, 14.649900436401367, 14.739999771118164, 14.710000038146973, 14.75, 14.868000030517578, 14.825499534606934, 14.85, 14.86, 14.87, 14.91, 14.87, 14.88, 14.89, 14.9, 14.9, 15.020000457763672, 14.6899995803833, 14.614999771118164, 14.640000343322754, 14.6899995803833, 14.739999771118164, 14.770000457763672, 14.75, 14.75, 14.75, 14.75, 14.73, 14.75, 14.79, 14.89, 14.79, 14.984999656677246, 14.880000114440918, 14.920000076293945, 14.889900207519531, 14.899900436401367, 14.899999618530273, 14.920000076293945, 14.97, 14.97, 14.9588, 14.89, 14.91, 14.91, 14.92, 14.96, 14.9496, 14.91670036315918, 14.654999732971191, 14.630000114440918, 14.59000015258789, 14.595000267028809, 14.579999923706055, 14.5, 14.7, 14.6471, 14.5, 14.47, 14.44, 14.43, 14.46, 14.5, 14.45, 14.5600004196167, 14.390000343322754, 14.420000076293945, 14.34000015258789, 14.385000228881836, 14.390000343322754, 14.260000228881836, 14.3, 14.44, 14.4, 14.27, 14.24, 14.27, 14.29, 14.3, 14.3, 14.725000381469727, 14.619999885559082, 14.625, 14.579999923706055, 14.484999656677246, 14.4399995803833, 14.40999984741211, 14.4, 14.44, 14.42, 14.4, 14.37, 14.36, 14.34, 14.4, 14.34, 14.25, 14.229999542236328, 14.21500015258789, 14.229999542236328, 14.225000381469727, 14.154999732971191, 14.085000038146973, 14.14, 14.09, 14.14, 14.11, 14.08, 14.1, 14.12, 14.15, 14.07, 14.135000228881836, 14.15999984741211, 14.079999923706055, 14.119999885559082, 14.085000038146973, 14.0600004196167, 14.0, 14.0997, 14.12, 14.01, 14.03, 14.01, 14.0, 13.98, 14.01, 13.98, 14.015000343322754, 14.069999694824219, 14.1899995803833, 14.199999809265137, 14.1899995803833, 14.170000076293945, 14.100000381469727, 14.1, 14.04, 14.07, 14.05, 14.18, 14.18, 14.07, 14.24, 14.04, 14.255000114440918, 14.324999809265137, 14.34000015258789, 14.520000457763672, 14.614999771118164, 14.550000190734863, 14.484999656677246, 14.49, 14.49, 14.52, 14.61, 14.55, 14.55, 14.54, 14.5871, 14.44, 14.800000190734863, 14.59000015258789, 14.4399995803833, 14.380000114440918, 14.305000305175781, 14.229999542236328, 14.300000190734863, 14.35, 14.35, 14.24, 14.2, 14.08, 14.0, 14.1, 14.21, 14.06, 14.020000457763672, 13.890000343322754, 13.850000381469727, 13.84000015258789, 13.819999694824219, 13.75, 13.770000457763672, 13.9, 13.8, 13.8, 13.81, 13.87, 13.87, 13.87, 13.9, 13.88, 14.404999732971191, 14.199999809265137, 14.199999809265137, 14.100000381469727, 14.129899978637695, 14.210000038146973, 14.255999565124512, 14.3, 14.3, 14.28, 14.33, 14.34, 14.34, 14.41, 14.5, 14.4399995803833, 14.579999923706055, 14.579999923706055, 14.65999984741211, 14.649999618530273, 14.649999618530273, 14.630000114440918, 14.67, 14.67, 14.67, 14.65, 14.61, 14.61, 14.65, 14.77, 14.61, 14.619999885559082, 14.329999923706055, 14.300000190734863, 14.255000114440918, 14.279999732971191, 14.270000457763672, 14.239999771118164, 14.2981, 14.2971, 14.25, 14.32, 14.3, 14.27, 14.27, 14.3172, 14.31, 14.59000015258789, 14.6850004196167, 14.880000114440918, 14.869999885559082, 14.728500366210938, 14.719900131225586, 14.65999984741211, 14.85, 14.85, 14.69, 14.75, 14.7, 14.7, 14.69, 14.78, 14.8131, 14.880000114440918, 14.970000267028809, 14.989999771118164, 14.895000457763672, 14.905400276184082, 14.885000228881836, 14.9399995803833, 14.94, 14.94, 14.98, 14.97, 14.98, 15.01, 14.97, 15.01, 15.0, 15.03499984741211, 14.949999809265137, 14.968500137329102, 15.020000457763672, 15.279999732971191, 15.239999771118164, 15.210000038146973, 15.29, 15.28, 15.29, 15.17, 15.21, 15.22, 15.26, 15.28, 15.34, 15.350000381469727, 14.944999694824219, 14.970000267028809, 15.0, 15.095000267028809, 15.125800132751465, 15.069999694824219, 15.15, 15.14, 15.12, 14.82, 14.72, 14.78, 14.84, 14.87, 14.84, 14.930000305175781, null, null, null, null, null, null, null, null, null, null, 14.869999885559082, 14.854999542236328, 14.765000343322754, 14.86, 17.3, 16.35, 16.01, 15.67, 15.66, 15.95, 16.18, 15.92, 16.040000915527344, 16.190000534057617, 16.110000610351562, 15.920000076293945, 15.829999923706055, 15.960000038146973, 16.100000381469727, 16.09, 16.1, 16.13, 16.25, 16.13, 16.12, 16.16, 16.24, 16.12, 15.949999809265137, 15.880000114440918, 15.890000343322754, 15.845000267028809, 15.789999961853027, 15.885000228881836, 15.82859992980957, 15.86, 15.8, 15.78, 15.73, 15.61, 15.71, 15.77, 15.81, 15.73, 15.760000228881836, 15.649999618530273, 15.600000381469727, 15.625100135803223, 15.65999984741211, 15.649999618530273, 15.628199577331543, 15.61, 15.6, 15.6, 15.71, 15.82, 15.77, 15.82, 15.85, 15.83, 15.960000038146973, 15.864999771118164, 16.024999618530273, 16.040000915527344, 16.114999771118164, 16.149999618530273, 16.065000534057617, 16.15, 16.13, 16.09, 16.2, 16.1, 16.06, 16.1, 16.23, 16.0994, 16.100000381469727, 16.020000457763672, 16.149999618530273, 16.1200008392334, 16.229999542236328, 16.270000457763672, 16.190000534057617, 16.27, 16.2, 16.12, 16.2, 16.11, 16.09, 16.1, 16.19, 16.12, 16.100000381469727, 16.014999389648438, 16.170000076293945, 16.25, 16.2450008392334, 16.329999923706055, 16.350000381469727, 16.42, 16.4, 16.3469, 16.37, 16.36, 16.3, 16.34, 16.3668, 16.42, 16.59000015258789, 16.485000610351562, 16.549999237060547, 16.55500030517578, 16.469999313354492, 16.479999542236328, 16.485000610351562, 16.5, 16.54, 16.54, 16.58, 16.56, 16.55, 16.55, 16.58, 16.52, 16.69499969482422, 16.780000686645508, 16.475000381469727, 16.299999237060547, 16.440000534057617, 16.46500015258789, 16.325000762939453, 16.45, 16.26, 16.45, 16.3, 16.26, 16.26, 16.26, 16.34, 16.28, 16.50659942626953, 16.600000381469727, 16.575000762939453, 16.440000534057617, 16.43000030517578, 16.389999389648438, 16.325000762939453, 16.3797, 16.28, 16.29, 16.58, 16.32, 16.3, 16.3, 16.4, 16.29, 16.5, 16.420000076293945, 16.415000915527344, 16.3700008392334, 16.420000076293945, 16.389999389648438, 16.454999923706055, 16.45, 16.45, 16.4238, 16.36, 16.36, 16.44, 16.49, 16.6488, 16.4259, 16.479999542236328, 16.436500549316406, 16.3799991607666, 16.399999618530273, 16.440000534057617, 16.360000610351562, 16.360000610351562, 16.38, 16.36, 16.36, 16.35, 16.35, 16.28, 16.39, 16.305, 16.3700008392334, 16.385000228881836, 16.344999313354492, 16.3799991607666, 16.364999771118164, 16.3700008392334, 16.3799991607666, 16.39, 16.4, 16.4, 16.48, 16.48, 16.43, 16.395, 16.4888, 16.39, 16.334999084472656, 16.415000915527344, 16.418899536132812, 16.540000915527344, 16.5, 16.485000610351562, 16.549999237060547, 16.77, 16.5, 16.69, 16.47, 16.45, 16.42, 16.45, 16.49, 16.4, 16.489999771118164, 16.219999313354492, 16.25, 16.31999969482422, 16.415000915527344, 16.415000915527344, 16.40999984741211, 16.44, 16.3811, 16.39, 16.2886, 16.3, 16.3, 17.13, 17.14, 16.55, 16.440000534057617, 16.40999984741211, 16.420000076293945, 16.389999389648438, 16.42650032043457, 16.459999084472656, 16.395000457763672, 16.4, 16.35, 16.3488, 16.47, 16.45, 16.46, 16.45, 16.53, 16.39, 16.420000076293945, 16.450000762939453, 16.469999313354492, 16.395000457763672, 16.389999389648438, 16.43000030517578, 16.439899444580078, 16.45, 16.45, 16.47, 16.48, 16.45, 16.46, 16.45, 16.51, 16.44, 16.375, 16.219900131225586, 16.20639991760254, 16.06999969482422, 16.1200008392334, 16.204999923706055, 16.329999923706055, 16.27, 16.26, 16.26, 16.21, 16.21, 16.14, 16.5, 16.77, 18.58, 17.389999389648438, 17.649999618530273, 17.520000457763672, 17.290000915527344, 17.344999313354492, 17.229999542236328, 17.299999237060547, 17.32, 17.23, 17.27, 16.9, 16.99, 17.095, 17.15, 17.28, 17.28, 14.350000381469727, 14.34000015258789, 14.300000190734863, 14.3100004196167, 14.319999694824219, 14.350000381469727, 14.3100004196167, 14.2822, 14.25, 14.24, 14.235, 14.23, 14.23, 14.25, 14.32, 14.24, 14.220000267028809, 14.180000305175781, 14.25, 14.239999771118164, 14.260000228881836, 14.239999771118164, 14.239999771118164, 14.2, 14.18, 14.17, 14.25, 14.25, 14.31, 14.32, 14.3299, 14.27, 14.229999542236328, 14.279999732971191, 14.270000457763672, 14.279999732971191, 14.289999961853027, 14.289999961853027, 14.300000190734863, 14.29, 14.29, 14.29, 14.29, 14.28, 14.27, 14.25, 14.29, 14.23, 14.319999694824219, 14.289999961853027, 14.270000457763672], "close": [14.48, 14.46, 14.45, 14.42, 14.4, 14.38, 14.539999961853027, 14.625, 14.694999694824219, 14.635000228881836, 14.734999656677246, 14.824999809265137, 14.8149995803833, 14.82, 14.86, 14.85, 14.87, 14.86, 14.86, 14.86, 14.84, 14.88, 14.699999809265137, 14.524999618530273, 14.574999809265137, 14.590100288391113, 14.6850004196167, 14.71500015258789, 14.729999542236328, 14.7, 14.75, 14.71, 14.72, 14.73, 14.74, 14.77, 14.775, 14.7401, 14.83549976348877, 14.856399536132812, 14.895600318908691, 14.875, 14.864999771118164, 14.879899978637695, 14.920000076293945, 14.9682, 14.85, 14.9, 14.89, 14.91, 14.89, 14.91, 14.94, 14.93, 14.654999732971191, 14.585000038146973, 14.569999694824219, 14.529999732971191, 14.563599586486816, 14.475000381469727, 14.4350004196167, 14.65, 14.5, 14.4499, 14.43, 14.4, 14.43, 14.41, 14.41, 14.42, 14.324999809265137, 14.385000228881836, 14.3149995803833, 14.324999809265137, 14.380000114440918, 14.25, 14.204999923706055, 14.24, 14.26, 14.32, 14.24, 14.23, 14.27, 14.275, 14.2984, 14.27, 14.58590030670166, 14.59000015258789, 14.515000343322754, 14.444999694824219, 14.4399995803833, 14.380000114440918, 14.3149995803833, 14.36, 14.4171, 14.4, 14.37, 14.36, 14.34, 14.32, 14.32, 14.32, 14.119999885559082, 14.145000457763672, 14.204999923706055, 14.21500015258789, 14.104999542236328, 14.055000305175781, 14.039999961853027, 14.08, 14.0607, 14.09, 14.08, 14.05, 14.07, 14.1, 14.03, 14.03, 14.031399726867676, 14.04010009765625, 14.074999809265137, 14.055000305175781, 14.024999618530273, 13.979999542236328, 13.968999862670898, 13.98, 14.01, 13.99, 14.02, 13.97, 13.98, 13.97, 13.96, 13.97, 13.930000305175781, 14.050000190734863, 14.1850004196167, 14.125, 14.135000228881836, 14.0649995803833, 14.0, 14.02, 14.01, 14.07, 14.05, 14.18, 14.12, 14.02, 14.04, 14.02, 14.204999923706055, 14.274999618530273, 14.3149995803833, 14.484999656677246, 14.550000190734863, 14.460000038146973, 14.432499885559082, 14.4899, 14.48, 14.5008, 14.52, 14.52, 14.54, 14.45, 14.44, 14.38, 14.585000038146973, 14.4350004196167, 14.335000038146973, 14.305000305175781, 14.182499885559082, 14.175000190734863, 14.1899995803833, 14.26, 14.2, 14.2335, 14.01, 14.0, 13.98, 14.09, 14.0408, 14.03, 13.885000228881836, 13.770000457763672, 13.795599937438965, 13.812000274658203, 13.710000038146973, 13.744999885559082, 13.770000457763672, 13.79, 13.78, 13.77, 13.81, 13.87, 13.87, 13.82, 13.82, 13.8696, 14.15999984741211, 14.175000190734863, 14.079899787902832, 14.015000343322754, 14.109999656677246, 14.164999961853027, 14.244999885559082, 14.289, 14.26, 14.25, 14.33, 14.34, 14.31, 14.3376, 14.35, 14.3149995803833, 14.558600425720215, 14.510000228881836, 14.625, 14.600000381469727, 14.614999771118164, 14.614999771118164, 14.65, 14.6591, 14.6654, 14.61, 14.61, 14.56, 14.6, 14.61, 14.6, 14.3100004196167, 14.295000076293945, 14.1850004196167, 14.234999656677246, 14.26099967956543, 14.225000381469727, 14.225000381469727, 14.21, 14.2, 14.2204, 14.3, 14.24, 14.27, 14.26, 14.31, 14.27, 14.479999542236328, 14.653599739074707, 14.824999809265137, 14.664999961853027, 14.719900131225586, 14.630000114440918, 14.630000114440918, 14.74, 14.68, 14.63, 14.7, 14.7, 14.7, 14.69, 14.71, 14.76, 14.850000381469727, 14.944999694824219, 14.867500305175781, 14.859999656677246, 14.864999771118164, 14.869999885559082, 14.914999961853027, 14.92, 14.9165, 14.91, 14.95, 14.98, 14.96, 14.93, 14.99, 14.9791, 14.880000114440918, 14.94629955291748, 14.904999732971191, 14.984999656677246, 15.0, 15.194999694824219, 15.1850004196167, 15.26, 15.25, 15.2799, 15.17, 15.21, 15.22, 15.25, 15.26, 15.2969, 14.925000190734863, 14.824999809265137, 14.9350004196167, 14.994999885559082, 15.085000038146973, 15.001399993896484, 15.03499984741211, 15.1, 15.1, 15.12, 14.72, 14.72, 14.78, 14.84, 14.83, 14.8199, 14.8100004196167, null, null, null, null, null, null, null, null, null, null, 14.859999656677246, 14.755000114440918, 14.75, 14.75, 16.2, 15.75, 15.65, 15.66, 15.63, 15.87, 15.92, 15.77, 16.024999618530273, 16.0049991607666, 15.914999961853027, 15.65839958190918, 15.720000267028809, 15.9350004196167, 16.100000381469727, 16.0893, 16.06, 16.12, 16.08, 16.09, 16.09, 16.14, 16.05, 16.0043, 15.6850004196167, 15.880000114440918, 15.773599624633789, 15.734999656677246, 15.789999961853027, 15.8100004196167, 15.734999656677246, 15.7, 15.75, 15.75, 15.56, 15.61, 15.57, 15.73, 15.61, 15.63, 15.5649995803833, 15.5649995803833, 15.524999618530273, 15.555000305175781, 15.645000457763672, 15.624500274658203, 15.595000267028809, 15.6, 15.59, 15.51, 15.71, 15.71, 15.77, 15.79, 15.82, 15.769, 15.779000282287598, 15.800000190734863, 15.984999656677246, 16.0049991607666, 16.094999313354492, 15.994999885559082, 16.030000686645508, 16.06, 16.0562, 16.09, 16.14, 16.06, 16.055, 16.09, 16.061, 16.0507, 15.864999771118164, 15.994999885559082, 16.049999237060547, 16.100000381469727, 16.219999313354492, 16.165000915527344, 16.049999237060547, 16.02, 16.1706, 16.07, 16.11, 16.09, 16.09, 16.1, 16.07, 16.12, 15.9350004196167, 15.975000381469727, 16.1299991607666, 16.174999237060547, 16.218599319458008, 16.229999542236328, 16.219999313354492, 16.3, 16.3, 16.33, 16.36, 16.27, 16.2, 16.3, 16.31, 16.4099, 16.334999084472656, 16.424999237060547, 16.539899826049805, 16.454999923706055, 16.40999984741211, 16.420000076293945, 16.43000030517578, 16.42, 16.46, 16.52, 16.58, 16.47, 16.53, 16.52, 16.5188, 16.52, 16.635000228881836, 16.395000457763672, 16.260000228881836, 16.190000534057617, 16.350000381469727, 16.311599731445312, 16.190000534057617, 16.26, 16.18, 16.19, 16.26, 16.21, 16.19, 16.19, 16.19, 16.241, 16.479999542236328, 16.540000915527344, 16.409700393676758, 16.389999389648438, 16.354999542236328, 16.30500030517578, 16.2450008392334, 16.26, 16.22, 16.28, 16.28, 16.29, 16.27, 16.3, 16.24, 16.28, 16.32550048828125, 16.375, 16.350000381469727, 16.315000534057617, 16.334999084472656, 16.375, 16.395000457763672, 16.4, 16.4337, 16.4196, 16.36, 16.36, 16.44, 16.42, 16.42, 16.41, 16.364999771118164, 16.354999542236328, 16.28499984741211, 16.344999313354492, 16.325000762939453, 16.235000610351562, 16.290000915527344, 16.24, 16.36, 16.3001, 16.35, 16.28, 16.25, 16.31, 16.25, 16.235000610351562, 16.299999237060547, 16.309999465942383, 16.34000015258789, 16.299999237060547, 16.334999084472656, 16.364999771118164, 16.2817, 16.3892, 16.3611, 16.48, 16.43, 16.38, 16.36, 16.4, 16.35, 16.299999237060547, 16.334999084472656, 16.399999618530273, 16.424999237060547, 16.420000076293945, 16.469999313354492, 16.5, 16.4, 16.45, 16.426, 16.4, 16.45, 16.4, 16.31, 16.35, 16.37, 16.19499969482422, 16.139999389648438, 16.235000610351562, 16.31999969482422, 16.375, 16.399999618530273, 16.264999389648438, 16.27, 16.27, 16.33, 16.2886, 16.3, 16.3, 16.46, 16.49, 16.51, 16.290000915527344, 16.389999389648438, 16.309999465942383, 16.325000762939453, 16.415000915527344, 16.350000381469727, 16.270000457763672, 16.35, 16.31, 16.34, 16.46, 16.4, 16.435, 16.4, 16.35, 16.37, 16.315000534057617, 16.44499969482422, 16.334999084472656, 16.360000610351562, 16.329999923706055, 16.329999923706055, 16.361000061035156, 16.44, 16.42, 16.42, 16.45, 16.45, 16.44, 16.44, 16.4379, 16.37, 16.024999618530273, 16.204999923706055, 15.975000381469727, 16.049999237060547, 16.06999969482422, 16.155000686645508, 16.25, 16.14, 16.17, 16.25, 16.21, 16.0, 16.14, 16.44, 16.61, 17.1999, 17.260000228881836, 17.399999618530273, 17.22209930419922, 17.155000686645508, 17.200000762939453, 17.209999084472656, 17.25, 17.21, 17.22, 17.25, 16.75, 16.99, 17.09, 14.41, 14.45, 14.3497, 14.295100212097168, 14.279000282287598, 14.265000343322754, 14.298100471496582, 14.3149995803833, 14.300000190734863, 14.204999923706055, 14.23, 14.2315, 14.24, 14.235, 14.22, 14.22, 14.23, 14.22, 14.19, 14.15999984741211, 14.170000076293945, 14.234999656677246, 14.229999542236328, 14.225000381469727, 14.229999542236328, 14.175000190734863, 14.15, 14.16, 14.14, 14.25, 14.2, 14.31, 14.25, 14.26, 14.27, 14.225000381469727, 14.260000228881836, 14.265000343322754, 14.279999732971191, 14.265000343322754, 14.255000114440918, 14.289999961853027, 14.2506, 14.26, 14.29, 14.25, 14.25, 14.24, 14.25, 14.22, 14.22, 14.274999618530273, 14.270000457763672, 14.270000457763672], "volume": [0, 0, 0, 0, 0, 0, 1101637, 874315, 674033, 491909, 456253, 1054387, 1111518, 0, 0, 0, 0, 0, 0, 0, 0, 0, 1929704, 1303787, 728599, 453834, 654742, 765640, 958217, 0, 0, 0, 0, 0, 0, 0, 0, 0, 1031733, 575743, 812497, 477619, 657910, 612364, 939891, 0, 0, 0, 0, 0, 0, 0, 0, 0, 1745523, 1066336, 507694, 545056, 683269, 731966, 1358542, 0, 0, 0, 0, 0, 0, 0, 0, 0, 1106813, 760286, 994591, 569700, 489901, 999926, 1367620, 0, 0, 0, 0, 0, 0, 0, 0, 0, 1356715, 507245, 940375, 683347, 579051, 702854, 1125668, 0, 0, 0, 0, 0, 0, 0, 0, 0, 1595908, 740089, 643308, 394237, 1046856, 772041, 1720095, 0, 0, 0, 0, 0, 0, 0, 0, 0, 1336569, 1121799, 893167, 611405, 1424280, 761902, 1449963, 0, 0, 0, 0, 0, 0, 0, 0, 0, 778177, 871866, 1547491, 1045460, 1327132, 1333384, 1289287, 0, 0, 0, 0, 0, 0, 0, 0, 0, 1336106, 2629348, 2018723, 2486316, 1467249, 1896969, 1593836, 0, 0, 0, 0, 0, 0, 0, 0, 0, 2219244, 1797137, 1119315, 1065923, 669385, 998150, 1564229, 0, 0, 0, 0, 0, 0, 0, 0, 0, 3398088, 1344837, 1141728, 969717, 866727, 1154201, 1716806, 0, 0, 0, 0, 0, 0, 0, 0, 0, 3135809, 1343709, 756218, 517185, 662544, 1049081, 1215595, 0, 0, 0, 0, 0, 0, 0, 0, 1467801, 857191, 858741, 660965, 651718, 829116, 1384261, 0, 0, 0, 0, 0, 0, 0, 0, 0, 800950, 554844, 795581, 642534, 513407, 517272, 1055052, 0, 0, 0, 0, 0, 0, 0, 0, 0, 1342692, 1119012, 1278285, 634725, 605675, 1003495, 1327110, 0, 0, 0, 0, 0, 0, 0, 0, 0, 1064940, 922100, 702616, 449689, 444392, 730744, 1073258, 0, 0, 0, 0, 0, 0, 0, 0, 0, 885110, 557455, 545186, 908518, 3546232, 1509541, 1798907, 0, 0, 0, 0, 0, 0, 0, 0, 0, 2254660, 1880031, 1308512, 563858, 723376, 1634968, 1497989, 0, 0, 0, 0, 0, 0, 0, 0, 0, 1416706, null, null, null, null, null, null, null, null, null, null, 3313800, 1592428, 1801702, 0, 0, 0, 0, 0, 0, 0, 0, 0, 6830214, 3355678, 1944921, 2774009, 3707064, 2095822, 2337644, 0, 0, 0, 0, 0, 0, 0, 0, 0, 2845928, 1713502, 1158953, 980819, 900321, 1169505, 1600483, 0, 0, 0, 0, 0, 0, 0, 0, 0, 2146743, 1101688, 1029910, 732423, 1150623, 910547, 1497391, 0, 0, 0, 0, 0, 0, 0, 0, 0, 950541, 841438, 653823, 575715, 645351, 860218, 1213793, 0, 0, 0, 0, 0, 0, 0, 0, 0, 1407950, 922182, 833767, 652507, 557726, 741159, 988606, 0, 0, 0, 0, 0, 0, 0, 0, 0, 1037466, 1015809, 700409, 525250, 661351, 1072092, 1576410, 0, 0, 0, 0, 0, 0, 0, 0, 0, 1464167, 862846, 903243, 714388, 832777, 982246, 1077135, 0, 0, 0, 0, 0, 0, 0, 0, 0, 1974548, 1804959, 2737462, 890262, 713604, 667421, 1124812, 0, 0, 0, 0, 0, 0, 0, 0, 0, 1329545, 3359053, 690967, 570719, 412581, 601276, 1544689, 0, 0, 0, 0, 0, 0, 0, 0, 0, 1477286, 1418228, 892432, 636092, 508395, 609242, 1269241, 0, 0, 0, 0, 0, 0, 0, 0, 0, 1233304, 798363, 859526, 411916, 446271, 648336, 1153413, 0, 0, 0, 0, 0, 0, 0, 0, 799460, 501147, 328936, 328559, 386181, 430544, 1058509, 0, 0, 0, 0, 0, 0, 0, 0, 0, 2880585, 727123, 560927, 850740, 737564, 779699, 1409780, 0, 0, 0, 0, 0, 0, 0, 0, 0, 1569526, 804615, 808092, 510401, 817059, 1169707, 1132594, 0, 0, 0, 0, 0, 0, 0, 0, 0, 1654594, 957199, 822825, 887277, 614338, 755853, 3160431, 0, 0, 0, 0, 0, 0, 0, 0, 0, 1742075, 710597, 618111, 442448, 489363, 715048, 1027312, 0, 0, 0, 0, 0, 0, 0, 0, 0, 1299469, 780863, 779520, 706782, 594337, 1448991, 2009275, 0, 0, 0, 0, 0, 0, 0, 0, 0, 8391387, 3499183, 2113488, 1418642, 1583812, 2886905, 3432301, 0, 0, 0, 0, 0, 0, 0, 0, 0, 34011356, 11402983, 9230703, 4351575, 4006264, 5522514, 7829593, 0, 0, 0, 0, 0, 0, 0, 0, 0, 15573219, 6282396, 7988223, 4883968, 3446067, 4891545, 4449854, 0, 0, 0, 0, 0, 0, 0, 0, 0, 4917477, 4261292, 2231275, 1215397, 1970749, 1963869, 3062109, 0, 0, 0, 0, 0, 0, 0, 0, 0, 7147562, 1738978, 0]}]}}], "error": null}}