{"chart": {"result": [{"meta": {"currency": "CNY", "symbol": "300394.SZ", "exchangeName": "SHZ", "fullExchangeName": "Shenzhen", "instrumentType": "EQUITY", "firstTradeDate": 1424136600, "regularMarketTime": 1772694274, "hasPrePostMarketData": false, "gmtoffset": 28800, "timezone": "CST", "exchangeTimezoneName": "Asia/Shanghai", "regularMarketPrice": 334.8, "fiftyTwoWeekHigh": 388.94, "fiftyTwoWeekLow": 40.793, "regularMarketDayHigh": 345.97, "regularMarketDayLow": 325.08, "regularMarketVolume": 32785993, "longName": "Suzhou TFC Optical Communication Co., Ltd.", "shortName": "SUZHOU TFC OPTICAL", "chartPreviousClose": 203.03, "previousClose": 335.56, "scale": 3, "priceHint": 2, "currentTradingPeriod": {"pre": {"timezone": "CST", "start": 1772760600, "end": 1772760600, "gmtoffset": 28800}, "regular": {"timezone": "CST", "start": 1772760600, "end": 1772780400, "gmtoffset": 28800}, "post": {"timezone": "CST", "start": 1772780400, "end": 1772780400, "gmtoffset": 28800}}, "tradingPeriods": {"pre": [[{"timezone": "CST", "start": 1767576600, "end": 1767576600, "gmtoffset": 28800}], [{"timezone": "CST", "start": 1767663000, "end": 1767663000, "gmtoffset": 28800}], [{"timezone": "CST", "start": 1767749400, "end": 1767749400, "gmtoffset": 28800}], [{"timezone": "CST", "start": 1767835800, "end": 1767835800, "gmtoffset": 28800}], [{"timezone": "CST", "start": 1767922200, "end": 1767922200, "gmtoffset": 28800}], [{"timezone": "CST", "start": 1768181400, "end": 1768181400, "gmtoffset": 28800}], [{"timezone": "CST", "start": 1768267800, "end": 1768267800, "gmtoffset": 28800}], [{"timezone": "CST", "start": 1768354200, "end": 1768354200, "gmtoffset": 28800}], [{"timezone": "CST", "start": 1768440600, "end": 1768440600, "gmtoffset": 28800}], [{"timezone": "CST", "start": 1768527000, "end": 1768527000, "gmtoffset": 28800}], [{"timezone": "CST", "start": 1768786200, "end": 1768786200, "gmtoffset": 28800}], [{"timezone": "CST", "start": 1768872600, "end": 1768872600, "gmtoffset": 28800}], [{"timezone": "CST", "start": 1768959000, "end": 1768959000, "gmtoffset": 28800}], [{"timezone": "CST", "start": 1769045400, "end": 1769045400, "gmtoffset": 28800}], [{"timezone": "CST", "start": 1769131800, "end": 1769131800, "gmtoffset": 28800}], [{"timezone": "CST", "start": 1769391000, "end": 1769391000, "gmtoffset": 28800}], [{"timezone": "CST", "start": 1769477400, "end": 1769477400, "gmtoffset": 28800}], [{"timezone": "CST", "start": 1769563800, "end": 1769563800, "gmtoffset": 28800}], [{"timezone": "CST", "start": 1769650200, "end": 1769650200, "gmtoffset": 28800}], [{"timezone": "CST", "start": 1769736600, "end": 1769736600, "gmtoffset": 28800}], [{"timezone": "CST", "start": 1769995800, "end": 1769995800, "gmtoffset": 28800}], [{"timezone": "CST", "start": 1770082200, "end": 1770082200, "gmtoffset": 28800}], [{"timezone": "CST", "start": 1770168600, "end": 1770168600, "gmtoffset": 28800}], [{"timezone": "CST", "start": 1770255000, "end": 1770255000, "gmtoffset": 28800}], [{"timezone": "CST", "start": 1770341400, "end": 1770341400, "gmtoffset": 28800}], [{"timezone": "CST", "start": 1770600600, "end": 1770600600, "gmtoffset": 28800}], [{"timezone": "CST", "start": 1770687000, "end": 1770687000, "gmtoffset": 28800}], [{"timezone": "CST", "start": 1770773400, "end": 1770773400, "gmtoffset": 28800}], [{"timezone": "CST", "start": 1770859800, "end": 1770859800, "gmtoffset": 28800}], [{"timezone": "CST", "start": 1770946200, "end": 1770946200, "gmtoffset": 28800}], [{"timezone": "CST", "start": 1771896600, "end": 1771896600, "gmtoffset": 28800}], [{"timezone": "CST", "start": 1771983000, "end": 1771983000, "gmtoffset": 28800}], [{"timezone": "CST", "start": 1772069400, "end": 1772069400, "gmtoffset": 28800}], [{"timezone": "CST", "start": 1772155800, "end": 1772155800, "gmtoffset": 28800}], [{"timezone": "CST", "start": 1772415000, "end": 1772415000, "gmtoffset": 28800}], [{"timezone": "CST", "start": 1772501400, "end": 1772501400, "gmtoffset": 28800}], [{"timezone": "CST", "start": 1772587800, "end": 1772587800, "gmtoffset": 28800}], [{"timezone": "CST", "start": 1772674200, "end": 1772674200, "gmtoffset": 28800}]], "post": [[{"timezone": "CST", "start": 1767596400, "end": 1767596400, "gmtoffset": 28800}], [{"timezone": "CST", "start": 1767682800, "end": 1767682800, "gmtoffset": 28800}], [{"timezone": "CST", "start": 1767769200, "end": 1767769200, "gmtoffset": 28800}], [{"timezone": "CST", "start": 1767855600, "end": 1767855600, "gmtoffset": 28800}], [{"timezone": "CST", "start": 1767942000, "end": 1767942000, "gmtoffset": 28800}], [{"timezone": "CST", "start": 1768201200, "end": 1768201200, "gmtoffset": 28800}], [{"timezone": "CST", "start": 1768287600, "end": 1768287600, "gmtoffset": 28800}], [{"timezone": "CST", "start": 1768374000, "end": 1768374000, "gmtoffset": 28800}], [{"timezone": "CST", "start": 1768460400, "end": 1768460400, "gmtoffset": 28800}], [{"timezone": "CST", "start": 1768546800, "end": 1768546800, "gmtoffset": 28800}], [{"timezone": "CST", "start": 1768806000, "end": 1768806000, "gmtoffset": 28800}], [{"timezone": "CST", "start": 1768892400, "end": 1768892400, "gmtoffset": 28800}], [{"timezone": "CST", "start": 1768978800, "end": 1768978800, "gmtoffset": 28800}], [{"timezone": "CST", "start": 1769065200, "end": 1769065200, "gmtoffset": 28800}], [{"timezone": "CST", "start": 1769151600, "end": 1769151600, "gmtoffset": 28800}], [{"timezone": "CST", "start": 1769410800, "end": 1769410800, "gmtoffset": 28800}], [{"timezone": "CST", "start": 1769497200, "end": 1769497200, "gmtoffset": 28800}], [{"timezone": "CST", "start": 1769583600, "end": 1769583600, "gmtoffset": 28800}], [{"timezone": "CST", "start": 1769670000, "end": 1769670000, "gmtoffset": 28800}], [{"timezone": "CST", "start": 1769756400, "end": 1769756400, "gmtoffset": 28800}], [{"timezone": "CST", "start": 1770015600, "end": 1770015600, "gmtoffset": 28800}], [{"timezone": "CST", "start": 1770102000, "end": 1770102000, "gmtoffset": 28800}], [{"timezone": "CST", "start": 1770188400, "end": 1770188400, "gmtoffset": 28800}], [{"timezone": "CST", "start": 1770274800, "end": 1770274800, "gmtoffset": 28800}], [{"timezone": "CST", "start": 1770361200, "end": 1770361200, "gmtoffset": 28800}], [{"timezone": "CST", "start": 1770620400, "end": 1770620400, "gmtoffset": 28800}], [{"timezone": "CST", "start": 1770706800, "end": 1770706800, "gmtoffset": 28800}], [{"timezone": "CST", "start": 1770793200, "end": 1770793200, "gmtoffset": 28800}], [{"timezone": "CST", "start": 1770879600, "end": 1770879600, "gmtoffset": 28800}], [{"timezone": "CST", "start": 1770966000, "end": 1770966000, "gmtoffset": 28800}], [{"timezone": "CST", "start": 1771916400, "end": 1771916400, "gmtoffset": 28800}], [{"timezone": "CST", "start": 1772002800, "end": 1772002800, "gmtoffset": 28800}], [{"timezone": "CST", "start": 1772089200, "end": 1772089200, "gmtoffset": 28800}], [{"timezone": "CST", "start": 1772175600, "end": 1772175600, "gmtoffset": 28800}], [{"timezone": "CST", "start": 1772434800, "end": 1772434800, "gmtoffset": 28800}], [{"timezone": "CST", "start": 1772521200, "end": 1772521200, "gmtoffset": 28800}], [{"timezone": "CST", "start": 1772607600, "end": 1772607600, "gmtoffset": 28800}], [{"timezone": "CST", "start": 1772694000, "end": 1772694000, "gmtoffset": 28800}]], "regular": [[{"timezone": "CST", "start": 1767576600, "end": 1767596400, "gmtoffset": 28800}], [{"timezone": "CST", "start": 1767663000, "end": 1767682800, "gmtoffset": 28800}], [{"timezone": "CST", "start": 1767749400, "end": 1767769200, "gmtoffset": 28800}], [{"timezone": "CST", "start": 1767835800, "end": 1767855600, "gmtoffset": 28800}], [{"timezone": "CST", "start": 1767922200, "end": 1767942000, "gmtoffset": 28800}], [{"timezone": "CST", "start": 1768181400, "end": 1768201200, "gmtoffset": 28800}], [{"timezone": "CST", "start": 1768267800, "end": 1768287600, "gmtoffset": 28800}], [{"timezone": "CST", "start": 1768354200, "end": 1768374000, "gmtoffset": 28800}], [{"timezone": "CST", "start": 1768440600, "end": 1768460400, "gmtoffset": 28800}], [{"timezone": "CST", "start": 1768527000, "end": 1768546800, "gmtoffset": 28800}], [{"timezone": "CST", "start": 1768786200, "end": 1768806000, "gmtoffset": 28800}], [{"timezone": "CST", "start": 1768872600, "end": 1768892400, "gmtoffset": 28800}], [{"timezone": "CST", "start": 1768959000, "end": 1768978800, "gmtoffset": 28800}], [{"timezone": "CST", "start": 1769045400, "end": 1769065200, "gmtoffset": 28800}], [{"timezone": "CST", "start": 1769131800, "end": 1769151600, "gmtoffset": 28800}], [{"timezone": "CST", "start": 1769391000, "end": 1769410800, "gmtoffset": 28800}], [{"timezone": "CST", "start": 1769477400, "end": 1769497200, "gmtoffset": 28800}], [{"timezone": "CST", "start": 1769563800, "end": 1769583600, "gmtoffset": 28800}], [{"timezone": "CST", "start": 1769650200, "end": 1769670000, "gmtoffset": 28800}], [{"timezone": "CST", "start": 1769736600, "end": 1769756400, "gmtoffset": 28800}], [{"timezone": "CST", "start": 1769995800, "end": 1770015600, "gmtoffset": 28800}], [{"timezone": "CST", "start": 1770082200, "end": 1770102000, "gmtoffset": 28800}], [{"timezone": "CST", "start": 1770168600, "end": 1770188400, "gmtoffset": 28800}], [{"timezone": "CST", "start": 1770255000, "end": 1770274800, "gmtoffset": 28800}], [{"timezone": "CST", "start": 1770341400, "end": 1770361200, "gmtoffset": 28800}], [{"timezone": "CST", "start": 1770600600, "end": 1770620400, "gmtoffset": 28800}], [{"timezone": "CST", "start": 1770687000, "end": 1770706800, "gmtoffset": 28800}], [{"timezone": "CST", "start": 1770773400, "end": 1770793200, "gmtoffset": 28800}], [{"timezone": "CST", "start": 1770859800, "end": 1770879600, "gmtoffset": 28800}], [{"timezone": "CST", "start": 1770946200, "end": 1770966000, "gmtoffset": 28800}], [{"timezone": "CST", "start": 1771896600, "end": 1771916400, "gmtoffset": 28800}], [{"timezone": "CST", "start": 1771983000, "end": 1772002800, "gmtoffset": 28800}], [{"timezone": "CST", "start": 1772069400, "end": 1772089200, "gmtoffset": 28800}], [{"timezone": "CST", "start": 1772155800, "end": 1772175600, "gmtoffset": 28800}], [{"timezone": "CST", "start": 1772415000, "end": 1772434800, "gmtoffset": 28800}], [{"timezone": "CST", "start": 1772501400, "end": 1772521200, "gmtoffset": 28800}], [{"timezone": "CST", "start": 1772587800, "end": 1772607600, "gmtoffset": 28800}], [{"timezone": "CST", "start": 1772674200, "end": 1772694000, "gmtoffset": 28800}]]}, "dataGranularity": "1h", "range": "", "validRanges": ["1d", "5d", "1mo", "3mo", "6mo", "1y", "2y", "5y", "10y", "ytd", "max"]}, "timestamp": [1767576600, 1767580200, 1767583800, 1767587400, 1767591000, 1767594600, 1767663000, 1767666600, 1767670200, 1767673800, 1767677400, 1767681000, 1767749400, 1767753000, 1767756600, 1767760200, 1767763800, 1767767400, 1767835800, 1767839400, 1767843000, 1767846600, 1767850200, 1767853800, 1767922200, 1767925800, 1767929400, 1767933000, 1767936600, 1767940200, 1768181400, 1768185000, 1768188600, 1768192200, 1768195800, 1768199400, 1768267800, 1768271400, 1768275000, 1768278600, 1768282200, 1768285800, 1768354200, 1768357800, 1768361400, 1768365000, 1768368600, 1768372200, 1768440600, 1768444200, 1768447800, 1768451400, 1768455000, 1768458600, 1768527000, 1768530600, 1768534200, 1768537800, 1768541400, 1768545000, 1768786200, 1768789800, 1768793400, 1768797000, 1768800600, 1768804200, 1768872600, 1768876200, 1768879800, 1768883400, 1768887000, 1768890600, 1768959000, 1768962600, 1768966200, 1768969800, 1768973400, 1768977000, 1769045400, 1769049000, 1769052600, 1769056200, 1769059800, 1769063400, 1769131800, 1769135400, 1769139000, 1769142600, 1769146200, 1769149800, 1769391000, 1769394600, 1769398200, 1769401800, 1769405400, 1769409000, 1769477400, 1769481000, 1769484600, 1769488200, 1769491800, 1769495400, 1769563800, 1769567400, 1769571000, 1769574600, 1769578200, 1769581800, 1769650200, 1769653800, 1769657400, 1769661000, 1769664600, 1769668200, 1769736600, 1769740200, 1769743800, 1769747400, 1769751000, 1769754600, 1769995800, 1769999400, 1770003000, 1770006600, 1770010200, 1770013800, 1770082200, 1770085800, 1770089400, 1770093000, 1770096600, 1770100200, 1770168600, 1770172200, 1770175800, 1770179400, 1770183000, 1770186600, 1770255000, 1770258600, 1770262200, 1770265800, 1770269400, 1770273000, 1770341400, 1770345000, 1770348600, 1770352200, 1770355800, 1770359400, 1770600600, 1770604200, 1770607800, 1770611400, 1770615000, 1770618600, 1770687000, 1770690600, 1770694200, 1770697800, 1770701400, 1770705000, 1770773400, 1770777000, 1770780600, 1770784200, 1770787800, 1770791400, 1770859800, 1770863400, 1770867000, 1770870600, 1770874200, 1770877800, 1770946200, 1770949800, 1770953400, 1770957000, 1770960600, 1770964200, 1771896600, 1771900200, 1771903800, 1771907400, 1771911000, 1771914600, 1771983000, 1771986600, 1771990200, 1771993800, 1771997400, 1772001000, 1772069400, 1772073000, 1772076600, 1772080200, 1772083800, 1772087400, 1772155800, 1772159400, 1772163000, 1772166600, 1772170200, 1772173800, 1772415000, 1772418600, 1772422200, 1772425800, 1772429400, 1772433000, 1772501400, 1772505000, 1772508600, 1772512200, 1772515800, 1772519400, 1772587800, 1772591400, 1772595000, 1772598600, 1772602200, 1772605800, 1772674200, 1772677800, 1772681400, 1772685000, 1772688600, 1772692200], "indicators": {"quote": [{"close": [204.75, 203.35000610351562, 203.35000610351562, 201.39999389648438, 203.60000610351562, 203.5, 198.1300048828125, 199.8699951171875, 199.8800048828125, 200.33999633789062, 201.7899932861328, 201.75999450683594, 204.16000366210938, 203.1999969482422, 203.19000244140625, 200.05999755859375, 202.0, 202.25, 198.0399932861328, 196.8000030517578, 196.7899932861328, 195.99000549316406, 195.30999755859375, 195.25, 195.74000549316406, 198.77000427246094, 198.83999633789062, 198.89999389648438, 198.27000427246094, 199.0, 195.94000244140625, 202.39999389648438, 202.39999389648438, 202.27000427246094, 202.10000610351562, 202.41000366210938, 195.10000610351562, 190.50999450683594, 190.35000610351562, 190.85000610351562, 191.16000366210938, null, 190.75999450683594, 191.74000549316406, 191.72000122070312, 193.64999389648438, 191.5500030517578, 191.69000244140625, 188.6300048828125, 188.35000610351562, 188.3300018310547, 190.0, 194.6999969482422, 193.97999572753906, 197.50999450683594, 199.64999389648438, 199.6699981689453, 199.36000061035156, 198.41000366210938, 198.00999450683594, 194.00999450683594, 192.1999969482422, 192.0, 193.57000732421875, 193.3699951171875, 193.24000549316406, 183.83999633789062, 183.19000244140625, 183.17999267578125, 185.41000366210938, 183.89999389648438, 184.89999389648438, 189.07000732421875, 188.4499969482422, 188.4600067138672, 189.10000610351562, 188.1199951171875, 188.72999572753906, 195.9600067138672, 194.27000427246094, 194.2899932861328, 197.0, 199.57000732421875, 199.97999572753906, 193.8000030517578, 188.39999389648438, 188.39999389648438, 189.4600067138672, 189.07000732421875, 189.19000244140625, 196.00999450683594, 196.49000549316406, 196.1199951171875, 196.67999267578125, 197.75, 195.9499969482422, 213.7899932861328, 213.3300018310547, 213.32000732421875, 210.41000366210938, 209.30999755859375, 210.0, 207.24000549316406, 212.2899932861328, 212.35000610351562, 214.8000030517578, 218.25999450683594, 219.3699951171875, 228.72999572753906, 230.66000366210938, 230.74000549316406, 225.99000549316406, 222.8000030517578, 222.60000610351562, 229.2899932861328, 250.38999938964844, 250.6999969482422, 253.64999389648438, 251.8000030517578, 248.50999450683594, null, null, null, null, null, null, 256.0400085449219, 260.20001220703125, 260.2900085449219, 264.1600036621094, 270.8999938964844, 270.3599853515625, 263.989990234375, 266.8999938964844, 266.8699951171875, 263.9599914550781, 266.0, 264.0, 248.77000427246094, 248.25999450683594, 248.25999450683594, 247.8300018310547, 249.58999633789062, 251.89999389648438, 249.0, 252.64999389648438, 252.72999572753906, 260.0, 256.54998779296875, 252.72000122070312, 299.3900146484375, 303.55999755859375, 303.55999755859375, 298.30999755859375, 296.3500061035156, 298.0, 285.8999938964844, 284.0400085449219, 284.05999755859375, 287.5299987792969, 289.1099853515625, 288.0, 292.3399963378906, 288.5, 288.5, 287.70001220703125, 288.55999755859375, 288.04998779296875, 316.6099853515625, 322.0, 322.0, 329.239990234375, 328.5, 328.760009765625, 314.8299865722656, 313.760009765625, 313.760009765625, 315.1700134277344, 311.69000244140625, 311.9100036621094, 350.5299987792969, 355.1099853515625, 355.1099853515625, 352.6099853515625, 351.29998779296875, 350.70001220703125, 334.1700134277344, 337.989990234375, 337.94000244140625, 341.82000732421875, 337.6400146484375, 341.510009765625, 366.1099853515625, 366.1499938964844, 365.1199951171875, 367.1000061035156, 365.0, 361.3500061035156, 349.0, 352.7099914550781, 352.8699951171875, 360.5799865722656, 363.5, 368.6000061035156, 384.04998779296875, 349.7900085449219, 349.79998779296875, 354.25, 348.0, 348.5199890136719, 344.510009765625, 343.55999755859375, 343.55999755859375, 339.3399963378906, 337.5, 334.5, 337.6600036621094, 339.19000244140625, 339.20001220703125, 336.54998779296875, 334.0, 336.6000061035156, 342.30999755859375, 333.9200134277344, 333.9200134277344, 336.760009765625, 332.92999267578125, 334.8800048828125], "high": [206.9499969482422, 205.0800018310547, 203.35000610351562, 203.60000610351562, 204.3000030517578, 204.0, 203.0, 199.9199981689453, 199.8800048828125, 200.6300048828125, 202.41000366210938, 202.17999267578125, 206.77000427246094, 204.9199981689453, 203.19000244140625, 203.19000244140625, 202.14999389648438, 202.36000061035156, 200.9499969482422, 198.7100067138672, 196.7899932861328, 196.7899932861328, 196.72000122070312, 195.94000244140625, 197.0800018310547, 201.74000549316406, 198.83999633789062, 200.1300048828125, 199.8000030517578, 199.5, 197.10000610351562, 203.9199981689453, 202.39999389648438, 204.8300018310547, 202.60000610351562, 202.74000549316406, 207.27999877929688, 195.07000732421875, 190.35000610351562, 192.22999572753906, 192.27000427246094, null, 194.8800048828125, 192.88999938964844, 191.72000122070312, 193.91000366210938, 194.85000610351562, 192.25999450683594, 194.0, 190.27000427246094, 188.3300018310547, 190.39999389648438, 197.11000061035156, 195.61000061035156, 199.1999969482422, 204.57000732421875, 199.6699981689453, 199.77999877929688, 200.6199951171875, 199.1999969482422, 198.55999755859375, 195.38999938964844, 192.0, 194.39999389648438, 198.0, 193.38999938964844, 193.1699981689453, 185.0800018310547, 183.17999267578125, 185.75999450683594, 185.67999267578125, 184.94000244140625, 189.3699951171875, 190.1999969482422, 188.4600067138672, 192.27999877929688, 189.9600067138672, 189.9199981689453, 200.5, 197.75999450683594, 194.2899932861328, 197.9499969482422, 200.64999389648438, 200.0, 199.77000427246094, 194.3300018310547, 188.39999389648438, 190.7899932861328, 189.63999938964844, 189.47999572753906, 196.74000549316406, 197.5399932861328, 196.1199951171875, 197.47000122070312, 198.47999572753906, 198.19000244140625, 216.38999938964844, 218.00999450683594, 213.32000732421875, 215.52999877929688, 211.22999572753906, 210.0800018310547, 218.32000732421875, 213.3699951171875, 212.35000610351562, 221.97999572753906, 219.9499969482422, 219.49000549316406, 230.75, 234.88999938964844, 230.74000549316406, 230.74000549316406, 226.74000549316406, 225.1699981689453, 236.00999450683594, 252.17999267578125, 250.6999969482422, 261.5, 254.38999938964844, 251.9600067138672, null, null, null, null, null, null, 268.8699951171875, 262.0, 260.2900085449219, 268.2799987792969, 272.0, 272.3500061035156, 275.17999267578125, 268.07000732421875, 266.8699951171875, 267.8900146484375, 266.5, 267.989990234375, 261.44000244140625, 250.5, 248.25999450683594, 249.67999267578125, 251.5, 252.6300048828125, 255.77999877929688, 253.25, 252.72999572753906, 267.989990234375, 264.0, 257.010009765625, 299.8999938964844, 303.55999755859375, 303.55999755859375, 303.55999755859375, 299.9800109863281, 298.0, 301.17999267578125, 291.67999267578125, 284.05999755859375, 289.9800109863281, 291.5, 289.5799865722656, 298.989990234375, 292.0199890136719, 288.5, 288.9200134277344, 290.7799987792969, 288.760009765625, 327.8800048828125, 324.9599914550781, 322.0, 329.239990234375, 333.4200134277344, 330.989990234375, 325.95001220703125, 314.67999267578125, 313.760009765625, 319.6499938964844, 316.2699890136719, 312.6400146484375, 358.8800048828125, 358.17999267578125, 355.1099853515625, 356.04998779296875, 355.989990234375, 351.6600036621094, 354.3900146484375, 338.989990234375, 337.94000244140625, 345.54998779296875, 343.5, 341.70001220703125, 368.95001220703125, 377.1499938964844, 365.1199951171875, 370.5899963378906, 371.0, 365.3599853515625, 351.0, 358.739990234375, 352.8699951171875, 361.32000732421875, 375.8900146484375, 369.6600036621094, 388.7799987792969, 388.8800048828125, 349.79998779296875, 363.5, 357.5, 351.0, 364.82000732421875, 349.3599853515625, 343.55999755859375, 343.55999755859375, 340.8900146484375, 337.6600036621094, 342.0, 343.010009765625, 339.20001220703125, 339.95001220703125, 338.80999755859375, 336.8699951171875, 342.7200012207031, 342.3699951171875, 333.9200134277344, 345.79998779296875, 336.9800109863281, 334.9599914550781], "low": [201.22999572753906, 202.3699951171875, 203.35000610351562, 200.0, 201.02999877929688, 203.0800018310547, 196.72000122070312, 196.8800048828125, 199.8800048828125, 199.61000061035156, 198.9199981689453, 201.39999389648438, 200.25, 202.00999450683594, 203.19000244140625, 200.0500030517578, 199.88999938964844, 201.0800018310547, 195.22999572753906, 195.72000122070312, 196.7899932861328, 195.39999389648438, 195.02000427246094, 195.10000610351562, 188.6199951171875, 194.0500030517578, 198.83999633789062, 197.67999267578125, 197.61000061035156, 198.17999267578125, 191.63999938964844, 195.3000030517578, 202.39999389648438, 200.38999938964844, 200.6999969482422, 200.99000549316406, 195.10000610351562, 188.60000610351562, 190.35000610351562, 190.13999938964844, 189.55999755859375, null, 189.02000427246094, 189.5800018310547, 191.72000122070312, 188.8800048828125, 189.22000122070312, 190.75, 188.60000610351562, 188.00999450683594, 188.3300018310547, 188.14999389648438, 189.67999267578125, 193.19000244140625, 193.0399932861328, 196.36000061035156, 199.6699981689453, 197.3300018310547, 197.02000427246094, 197.5, 191.2899932861328, 192.0, 192.0, 192.0, 192.3699951171875, 192.3300018310547, 182.77000427246094, 182.39999389648438, 183.17999267578125, 183.16000366210938, 183.17999267578125, 183.0, 183.60000610351562, 187.7899932861328, 188.4600067138672, 188.25999450683594, 187.8800048828125, 188.11000061035156, 186.41000366210938, 194.10000610351562, 194.2899932861328, 193.77999877929688, 196.5, 199.05999755859375, 193.00999450683594, 188.33999633789062, 188.39999389648438, 188.30999755859375, 188.5, 188.39999389648438, 186.6999969482422, 193.1999969482422, 196.1199951171875, 195.58999633789062, 195.3000030517578, 195.8800048828125, 197.60000610351562, 211.0800018310547, 213.32000732421875, 210.02000427246094, 209.16000366210938, 208.44000244140625, 205.88999938964844, 205.07000732421875, 212.35000610351562, 212.35000610351562, 212.97999572753906, 217.00999450683594, 219.47000122070312, 227.19000244140625, 230.74000549316406, 225.8300018310547, 222.02000427246094, 221.8300018310547, 220.6999969482422, 227.64999389648438, 250.6999969482422, 250.36000061035156, 249.0, 248.24000549316406, null, null, null, null, null, null, 253.5, 250.9199981689453, 260.2900085449219, 260.2900085449219, 264.2699890136719, 268.0199890136719, 252.22000122070312, 263.0799865722656, 266.8699951171875, 263.29998779296875, 260.07000732421875, 264.0, 244.8800048828125, 244.44000244140625, 248.25999450683594, 246.17999267578125, 246.64999389648438, 249.85000610351562, 242.0, 246.67999267578125, 252.72999572753906, 252.72999572753906, 255.89999389648438, 252.02000427246094, 266.5299987792969, 294.8900146484375, 303.55999755859375, 296.0199890136719, 296.0, 295.7699890136719, 285.260009765625, 283.3699951171875, 284.05999755859375, 283.0299987792969, 287.3500061035156, 286.6199951171875, 287.010009765625, 285.07000732421875, 288.5, 286.1199951171875, 287.69000244140625, 287.0, 298.0299987792969, 313.7699890136719, 322.0, 322.0, 327.6000061035156, 328.1099853515625, 310.239990234375, 311.1300048828125, 313.760009765625, 313.760009765625, 310.2799987792969, 309.0, 328.29998779296875, 350.0199890136719, 355.1099853515625, 350.9200134277344, 351.0, 350.5, 332.1199951171875, 328.8900146484375, 337.94000244140625, 337.94000244140625, 337.5, 337.1199951171875, 344.5199890136719, 361.0299987792969, 365.1199951171875, 364.29998779296875, 363.6000061035156, 360.6000061035156, 340.95001220703125, 347.6099853515625, 352.8699951171875, 352.8699951171875, 360.82000732421875, 362.8999938964844, 366.0, 349.0199890136719, 349.79998779296875, 348.0, 347.45001220703125, 346.6400146484375, 339.2099914550781, 341.9200134277344, 343.55999755859375, 339.0, 334.80999755859375, 332.75, 324.6499938964844, 336.0, 339.20001220703125, 334.5400085449219, 333.3299865722656, 333.29998779296875, 325.9800109863281, 333.4200134277344, 333.9200134277344, 333.9200134277344, 330.0, 331.7300109863281], "volume": [11972701, 4925454, 0, 21744148, 5340501, 0, 16599975, 4036525, 0, 23074605, 4927052, 0, 15403541, 4351156, 0, 22877972, 4435038, 0, 11567200, 5971486, 0, 20718712, 4371461, 0, 14032506, 9459066, 0, 27408407, 3841798, 0, 14670799, 12407318, 0, 31994432, 3944417, 0, 21508162, 14093667, 0, 38207318, 2271794, null, 13503860, 4908724, 0, 24445508, 6891180, 0, 9490285, 3837630, 0, 15415986, 15401529, 0, 16320845, 17799507, 0, 37575066, 4951238, 0, 16198825, 5132531, 0, 23165965, 3505550, 0, 16812744, 4937020, 0, 23672985, 3352910, 0, 10866313, 4171893, 0, 18689033, 3490941, 0, 25688253, 4875042, 0, 33479402, 12031961, 0, 18383452, 10297939, 0, 31676119, 4300242, 0, 17944092, 8599431, 0, 29531539, 6801180, 0, 36198968, 11006943, 0, 50466824, 4260861, 0, 23343909, 7760363, 0, 41944307, 8228760, 0, 28279889, 12432414, 0, 44544820, 6153862, 0, 26169798, 24489364, 0, 60748920, 6771155, 0, null, null, null, null, null, null, 34808412, 9849201, 0, 49369243, 8073715, 0, 26436943, 4832125, 0, 34603687, 6196890, 0, 23914861, 7595091, 0, 33487556, 3810099, 0, 19140706, 5493515, 0, 38393020, 7241840, 0, 31717706, 13035751, 0, 49719668, 3959916, 0, 18464896, 5597297, 0, 26566693, 3146331, 0, 19797026, 5439947, 0, 27370054, 4067118, 0, 28884763, 5275447, 0, 38438863, 6232647, 0, 0, 3729237, 0, 21693361, 4060234, 0, 23733722, 3218235, 0, 29658071, 2832137, 0, 15519802, 7365720, 0, 25832735, 3353798, 0, 25350509, 7440248, 0, 35176199, 3995228, 0, 19057778, 5809475, 0, 27333973, 9332127, 0, 17291909, 15776997, 0, 40584996, 8449987, 0, 23904286, 5506794, 0, 33012995, 6900508, 0, 15344041, 4810901, 0, 22766153, 2981856, 0, 17716210, 4625067, 0, 26224414, 3985865, 0], "open": [206.9499969482422, 204.75, 203.35000610351562, 203.35000610351562, 201.41000366210938, 203.60000610351562, 200.13999938964844, 198.11000061035156, 199.8800048828125, 199.8800048828125, 200.27000427246094, 201.75, 205.35000610351562, 204.02000427246094, 203.19000244140625, 203.19000244140625, 200.0800018310547, 201.97999572753906, 199.50999450683594, 198.0500030517578, 196.7899932861328, 196.7899932861328, 195.9499969482422, 195.2100067138672, 192.0800018310547, 196.08999633789062, 198.83999633789062, 198.83999633789062, 198.89999389648438, 198.22000122070312, 196.1999969482422, 195.77000427246094, 202.39999389648438, 202.39999389648438, 202.16000366210938, 202.10000610351562, 200.1999969482422, 195.07000732421875, 190.35000610351562, 190.35000610351562, 190.72000122070312, null, 192.8000030517578, 190.77000427246094, 191.72000122070312, 191.72000122070312, 193.64999389648438, 191.52999877929688, 189.19000244140625, 188.6999969482422, 188.3300018310547, 188.3300018310547, 190.02000427246094, 194.6999969482422, 196.32000732421875, 197.5, 199.6699981689453, 199.6699981689453, 199.5, 198.39999389648438, 193.47999572753906, 194.00999450683594, 192.0, 192.0, 198.0, 193.3800048828125, 192.5, 183.83999633789062, 183.17999267578125, 183.17999267578125, 185.25, 183.89999389648438, 183.60000610351562, 189.05999755859375, 188.4600067138672, 188.4600067138672, 189.00999450683594, 188.11000061035156, 188.38999938964844, 195.97999572753906, 194.2899932861328, 194.2899932861328, 197.0, 199.5800018310547, 197.89999389648438, 193.8000030517578, 188.39999389648438, 188.39999389648438, 189.4199981689453, 189.00999450683594, 188.47000122070312, 196.27999877929688, 196.1199951171875, 196.1199951171875, 196.6199951171875, 197.72000122070312, 197.60000610351562, 213.8000030517578, 213.32000732421875, 213.32000732421875, 210.42999267578125, 209.30999755859375, 216.89999389648438, 207.22000122070312, 212.35000610351562, 212.35000610351562, 214.64999389648438, 218.22000122070312, 219.7899932861328, 228.75999450683594, 230.74000549316406, 230.74000549316406, 225.8800048828125, 222.8000030517578, 220.6999969482422, 229.63999938964844, 250.6999969482422, 250.6999969482422, 253.5399932861328, 251.77999877929688, null, null, null, null, null, null, 253.5, 256.0, 260.2900085449219, 260.2900085449219, 264.2699890136719, 270.8999938964844, 272.17999267578125, 263.8999938964844, 266.8699951171875, 266.8699951171875, 263.8900146484375, 266.1300048828125, 255.6199951171875, 248.6199951171875, 248.25999450683594, 248.25999450683594, 247.77000427246094, 249.85000610351562, 255.0, 249.10000610351562, 252.72999572753906, 252.72999572753906, 259.8999938964844, 256.54998779296875, 275.0, 299.0, 303.55999755859375, 303.55999755859375, 298.1499938964844, 296.3299865722656, 294.9200134277344, 286.1000061035156, 284.05999755859375, 284.05999755859375, 287.5199890136719, 289.4200134277344, 289.0, 292.0199890136719, 288.5, 288.5, 287.69000244140625, 288.5400085449219, 300.0, 316.489990234375, 322.0, 322.0, 329.3299865722656, 328.3999938964844, 325.0, 314.3299865722656, 313.760009765625, 313.760009765625, 315.3399963378906, 311.69000244140625, 328.29998779296875, 350.2699890136719, 355.1099853515625, 355.1099853515625, 352.6099853515625, 351.29998779296875, 352.70001220703125, 334.45001220703125, 337.94000244140625, 337.94000244140625, 341.989990234375, 337.6400146484375, 344.5199890136719, 365.8399963378906, 365.1199951171875, 365.1199951171875, 366.7200012207031, 365.0, 341.1099853515625, 349.0, 352.8699951171875, 352.8699951171875, 360.82000732421875, 363.510009765625, 366.6600036621094, 384.05999755859375, 349.79998779296875, 349.79998779296875, 354.1199951171875, 348.19000244140625, 362.989990234375, 344.79998779296875, 343.55999755859375, 343.55999755859375, 339.3399963378906, 337.4599914550781, 327.6499938964844, 337.510009765625, 339.20001220703125, 339.20001220703125, 336.29998779296875, 334.29998779296875, 342.0400085449219, 341.6000061035156, 333.9200134277344, 333.9200134277344, 336.70001220703125, 332.92999267578125]}]}}], "error": null}}